Workbook

Sheet Cash
A1: Company Name | C1: ABC Ltd | F1: Remind | G1: - "+ve" for income, "-ve" for expenses
A2: Period | C2: 1.1.25-31.12.25
A3: Cash record
A4: COA: | C4: Director's C/A
A5: Reference name: | C5: Cash
AY8: For peachtree import use
B9: Date | C9: Particular | G9: Cash in | H9: Cash out | I9: Balance | K9: Control | M9: Interbank | O9: Computer equipment | P9: Fixture & furniture | R9: Director's C/A | T9: Trade receivable | U9: Trade payable | V9: Accruals | X9: Sales | Y9: Purchases | AA9: Advertisement | AB9: Bank charges | AC9: Business registration fee | AD9: Company secretary fee | AE9: Electricity & water | AF9: Entertainment | AG9: Insurance | AH9: Legal and professional fee | AI9: Local travelling | AJ9: Postage & courier | AK9: Printing & stationery | AL9: Rental expenses | AM9: Staff welfare | AN9: Stamp duty | AO9: Telecommunication | AP9: Transportation | AT9: Date | AU9: Reference | AW9: Number of Distributions | AX9: G/L Account (Bank) | AY9: G/L Account (Nature) | AZ9: Description | BA9: Bank (Amount$) | BB9: Nature (Amount$)
A10: No. | B10: Date | C10: Nature | D10: Payer / (Payee) | E10: Invoice no. (Cheque no.) | F10: Details | AY10: Please don't move this column
A11: 0 | B11: 45658 | C11: Cash opening | I11: 10000
A12: 2501-001 | B12: 45658 | C12: Sales | D12: Sale invoce #12345 | F12: ABC customer | G12: 1000 | I12: =I11+G12+H12 -> 11000 | K12: =SUM(G12:H12)-SUM(L12:AQ12) -> 0 | M12: =IF($C12=M$9,$G12+$H12,0) -> 0 | O12: =IF($C12=O$9,$G12+$H12,0) -> 0 | P12: =IF($C12=P$9,$G12+$H12,0) -> 0 | R12: =IF($C12=R$9,$G12+$H12,0) -> 0 | T12: =IF($C12=T$9,$G12+$H12,0) -> 0 | U12: =IF($C12=U$9,$G12+$H12,0) -> 0 | V12: =IF($C12=V$9,$G12+$H12,0) -> 0 | X12: =IF($C12=X$9,$G12+$H12,0) -> 1000 | Y12: =IF($C12=Y$9,$G12+$H12,0) -> 0 | AA12: =IF($C12=AA$9,$G12+$H12,0) -> 0 | AB12: =IF($C12=AB$9,$G12+$H12,0) -> 0 | AC12: =IF($C12=AC$9,$G12+$H12,0) -> 0 | AD12: =IF($C12=AD$9,$G12+$H12,0) -> 0 | AE12: =IF($C12=AE$9,$G12+$H12,0) -> 0 | AF12: =IF($C12=AF$9,$G12+$H12,0) -> 0 | AG12: =IF($C12=AG$9,$G12+$H12,0) -> 0 | AH12: =IF($C12=AH$9,$G12+$H12,0) -> 0 | ... AP12: =IF($C12=AP$9,$G12+$H12,0) -> 0 | AT12: =IF(B12="","",B12) -> 45658 | AU12: =IF(C12="","",$C$5&"-"&A12) -> Cash-2501-001 | AW12: =IF(AU12="","",COUNTIF(AU:AU,AU12)*2) -> 2 | AX12: =IF(C12="","",IF($C$4="","",VLOOKUP($C$4,'Chart of Accounts'!$A:$B,2,FALSE))) -> 2400 | AY12: =IF(C12="","",VLOOKUP(C:C,'Chart of Accounts'!$A:$B,2,FALSE)) -> 4000 | AZ12: =IF(C12="","",C12&":"&D12&IF(E12="",""," - "&E12)&IF(F12="",""," - "&F12)) -> Sales:Sale invoce #12345 - ABC customer | BA12: =SUM(G12:H12) -> 1000 | BB12: =-SUM(G12:H12) -> -1000
A13: 2501-002 | B13: 45658 | C13: Local travelling | D13: Travelling | H13: -500 | I13: =I12+G13+H13 -> 10500 | K13: =SUM(G13:H13)-SUM(L13:AQ13) -> 0 | M13: =IF($C13=M$9,$G13+$H13,0) -> 0 | O13: =IF($C13=O$9,$G13+$H13,0) -> 0 | P13: =IF($C13=P$9,$G13+$H13,0) -> 0 | R13: =IF($C13=R$9,$G13+$H13,0) -> 0 | T13: =IF($C13=T$9,$G13+$H13,0) -> 0 | U13: =IF($C13=U$9,$G13+$H13,0) -> 0 | V13: =IF($C13=V$9,$G13+$H13,0) -> 0 | X13: =IF($C13=X$9,$G13+$H13,0) -> 0 | Y13: =IF($C13=Y$9,$G13+$H13,0) -> 0 | AA13: =IF($C13=AA$9,$G13+$H13,0) -> 0 | AB13: =IF($C13=AB$9,$G13+$H13,0) -> 0 | AC13: =IF($C13=AC$9,$G13+$H13,0) -> 0 | AD13: =IF($C13=AD$9,$G13+$H13,0) -> 0 | AE13: =IF($C13=AE$9,$G13+$H13,0) -> 0 | AF13: =IF($C13=AF$9,$G13+$H13,0) -> 0 | AG13: =IF($C13=AG$9,$G13+$H13,0) -> 0 | AH13: =IF($C13=AH$9,$G13+$H13,0) -> 0 | ... AP13: =IF($C13=AP$9,$G13+$H13,0) -> 0 | AT13: =IF(B13="","",B13) -> 45658 | AU13: =IF(C13="","",$C$5&"-"&A13) -> Cash-2501-002 | AW13: =IF(AU13="","",COUNTIF(AU:AU,AU13)*2) -> 2 | AX13: =IF(C13="","",IF($C$4="","",VLOOKUP($C$4,'Chart of Accounts'!$A:$B,2,FALSE))) -> 2400 | AY13: =IF(C13="","",VLOOKUP(C:C,'Chart of Accounts'!$A:$B,2,FALSE)) -> 6750 | AZ13: =IF(C13="","",C13&":"&D13&IF(E13="",""," - "&E13)&IF(F13="",""," - "&F13)) -> Local travelling:Travelling | BA13: =SUM(G13:H13) -> -500 | BB13: =-SUM(G13:H13) -> 500
A14: 2501-003 | I14: =I13+G14+H14 -> 10500 | K14: =SUM(G14:H14)-SUM(L14:AQ14) -> 0 | M14: =IF($C14=M$9,$G14+$H14,0) -> 0 | O14: =IF($C14=O$9,$G14+$H14,0) -> 0 | P14: =IF($C14=P$9,$G14+$H14,0) -> 0 | R14: =IF($C14=R$9,$G14+$H14,0) -> 0 | T14: =IF($C14=T$9,$G14+$H14,0) -> 0 | U14: =IF($C14=U$9,$G14+$H14,0) -> 0 | V14: =IF($C14=V$9,$G14+$H14,0) -> 0 | X14: =IF($C14=X$9,$G14+$H14,0) -> 0 | Y14: =IF($C14=Y$9,$G14+$H14,0) -> 0 | AA14: =IF($C14=AA$9,$G14+$H14,0) -> 0 | AB14: =IF($C14=AB$9,$G14+$H14,0) -> 0 | AC14: =IF($C14=AC$9,$G14+$H14,0) -> 0 | AD14: =IF($C14=AD$9,$G14+$H14,0) -> 0 | AE14: =IF($C14=AE$9,$G14+$H14,0) -> 0 | AF14: =IF($C14=AF$9,$G14+$H14,0) -> 0 | AG14: =IF($C14=AG$9,$G14+$H14,0) -> 0 | AH14: =IF($C14=AH$9,$G14+$H14,0) -> 0 | ... AP14: =IF($C14=AP$9,$G14+$H14,0) -> 0 | AT14: =IF(B14="","",B14) | AU14: =IF(C14="","",$C$5&"-"&A14) | AW14: =IF(AU14="","",COUNTIF(AU:AU,AU14)*2) | AX14: =IF(C14="","",IF($C$4="","",VLOOKUP($C$4,'Chart of Accounts'!$A:$B,2,FALSE))) | AY14: =IF(C14="","",VLOOKUP(C:C,'Chart of Accounts'!$A:$B,2,FALSE)) | AZ14: =IF(C14="","",C14&":"&D14&IF(E14="",""," - "&E14)&IF(F14="",""," - "&F14)) | BA14: =SUM(G14:H14) -> 0 | BB14: =-SUM(G14:H14) -> 0
A15: 2501-004 | I15: =I14+G15+H15 -> 10500 | K15: =SUM(G15:H15)-SUM(L15:AQ15) -> 0 | M15: =IF($C15=M$9,$G15+$H15,0) -> 0 | O15: =IF($C15=O$9,$G15+$H15,0) -> 0 | P15: =IF($C15=P$9,$G15+$H15,0) -> 0 | R15: =IF($C15=R$9,$G15+$H15,0) -> 0 | T15: =IF($C15=T$9,$G15+$H15,0) -> 0 | U15: =IF($C15=U$9,$G15+$H15,0) -> 0 | V15: =IF($C15=V$9,$G15+$H15,0) -> 0 | X15: =IF($C15=X$9,$G15+$H15,0) -> 0 | Y15: =IF($C15=Y$9,$G15+$H15,0) -> 0 | AA15: =IF($C15=AA$9,$G15+$H15,0) -> 0 | AB15: =IF($C15=AB$9,$G15+$H15,0) -> 0 | AC15: =IF($C15=AC$9,$G15+$H15,0) -> 0 | AD15: =IF($C15=AD$9,$G15+$H15,0) -> 0 | AE15: =IF($C15=AE$9,$G15+$H15,0) -> 0 | AF15: =IF($C15=AF$9,$G15+$H15,0) -> 0 | AG15: =IF($C15=AG$9,$G15+$H15,0) -> 0 | AH15: =IF($C15=AH$9,$G15+$H15,0) -> 0 | ... AP15: =IF($C15=AP$9,$G15+$H15,0) -> 0 | AT15: =IF(B15="","",B15) | AU15: =IF(C15="","",$C$5&"-"&A15) | AW15: =IF(AU15="","",COUNTIF(AU:AU,AU15)*2) | AX15: =IF(C15="","",IF($C$4="","",VLOOKUP($C$4,'Chart of Accounts'!$A:$B,2,FALSE))) | AY15: =IF(C15="","",VLOOKUP(C:C,'Chart of Accounts'!$A:$B,2,FALSE)) | AZ15: =IF(C15="","",C15&":"&D15&IF(E15="",""," - "&E15)&IF(F15="",""," - "&F15)) | BA15: =SUM(G15:H15) -> 0 | BB15: =-SUM(G15:H15) -> 0
A16: 2501-005 | I16: =I15+G16+H16 -> 10500 | K16: =SUM(G16:H16)-SUM(L16:AQ16) -> 0 | M16: =IF($C16=M$9,$G16+$H16,0) -> 0 | O16: =IF($C16=O$9,$G16+$H16,0) -> 0 | P16: =IF($C16=P$9,$G16+$H16,0) -> 0 | R16: =IF($C16=R$9,$G16+$H16,0) -> 0 | T16: =IF($C16=T$9,$G16+$H16,0) -> 0 | U16: =IF($C16=U$9,$G16+$H16,0) -> 0 | V16: =IF($C16=V$9,$G16+$H16,0) -> 0 | X16: =IF($C16=X$9,$G16+$H16,0) -> 0 | Y16: =IF($C16=Y$9,$G16+$H16,0) -> 0 | AA16: =IF($C16=AA$9,$G16+$H16,0) -> 0 | AB16: =IF($C16=AB$9,$G16+$H16,0) -> 0 | AC16: =IF($C16=AC$9,$G16+$H16,0) -> 0 | AD16: =IF($C16=AD$9,$G16+$H16,0) -> 0 | AE16: =IF($C16=AE$9,$G16+$H16,0) -> 0 | AF16: =IF($C16=AF$9,$G16+$H16,0) -> 0 | AG16: =IF($C16=AG$9,$G16+$H16,0) -> 0 | AH16: =IF($C16=AH$9,$G16+$H16,0) -> 0 | ... AP16: =IF($C16=AP$9,$G16+$H16,0) -> 0 | AT16: =IF(B16="","",B16) | AU16: =IF(C16="","",$C$5&"-"&A16) | AW16: =IF(AU16="","",COUNTIF(AU:AU,AU16)*2) | AX16: =IF(C16="","",IF($C$4="","",VLOOKUP($C$4,'Chart of Accounts'!$A:$B,2,FALSE))) | AY16: =IF(C16="","",VLOOKUP(C:C,'Chart of Accounts'!$A:$B,2,FALSE)) | AZ16: =IF(C16="","",C16&":"&D16&IF(E16="",""," - "&E16)&IF(F16="",""," - "&F16)) | BA16: =SUM(G16:H16) -> 0 | BB16: =-SUM(G16:H16) -> 0
A17: 2501-006 | I17: =I16+G17+H17 -> 10500 | K17: =SUM(G17:H17)-SUM(L17:AQ17) -> 0 | M17: =IF($C17=M$9,$G17+$H17,0) -> 0 | O17: =IF($C17=O$9,$G17+$H17,0) -> 0 | P17: =IF($C17=P$9,$G17+$H17,0) -> 0 | R17: =IF($C17=R$9,$G17+$H17,0) -> 0 | T17: =IF($C17=T$9,$G17+$H17,0) -> 0 | U17: =IF($C17=U$9,$G17+$H17,0) -> 0 | V17: =IF($C17=V$9,$G17+$H17,0) -> 0 | X17: =IF($C17=X$9,$G17+$H17,0) -> 0 | Y17: =IF($C17=Y$9,$G17+$H17,0) -> 0 | AA17: =IF($C17=AA$9,$G17+$H17,0) -> 0 | AB17: =IF($C17=AB$9,$G17+$H17,0) -> 0 | AC17: =IF($C17=AC$9,$G17+$H17,0) -> 0 | AD17: =IF($C17=AD$9,$G17+$H17,0) -> 0 | AE17: =IF($C17=AE$9,$G17+$H17,0) -> 0 | AF17: =IF($C17=AF$9,$G17+$H17,0) -> 0 | AG17: =IF($C17=AG$9,$G17+$H17,0) -> 0 | AH17: =IF($C17=AH$9,$G17+$H17,0) -> 0 | ... AP17: =IF($C17=AP$9,$G17+$H17,0) -> 0 | AT17: =IF(B17="","",B17) | AU17: =IF(C17="","",$C$5&"-"&A17) | AW17: =IF(AU17="","",COUNTIF(AU:AU,AU17)*2) | AX17: =IF(C17="","",IF($C$4="","",VLOOKUP($C$4,'Chart of Accounts'!$A:$B,2,FALSE))) | AY17: =IF(C17="","",VLOOKUP(C:C,'Chart of Accounts'!$A:$B,2,FALSE)) | AZ17: =IF(C17="","",C17&":"&D17&IF(E17="",""," - "&E17)&IF(F17="",""," - "&F17)) | BA17: =SUM(G17:H17) -> 0 | BB17: =-SUM(G17:H17) -> 0
A18: 2501-007 | I18: =I17+G18+H18 -> 10500 | K18: =SUM(G18:H18)-SUM(L18:AQ18) -> 0 | M18: =IF($C18=M$9,$G18+$H18,0) -> 0 | O18: =IF($C18=O$9,$G18+$H18,0) -> 0 | P18: =IF($C18=P$9,$G18+$H18,0) -> 0 | R18: =IF($C18=R$9,$G18+$H18,0) -> 0 | T18: =IF($C18=T$9,$G18+$H18,0) -> 0 | U18: =IF($C18=U$9,$G18+$H18,0) -> 0 | V18: =IF($C18=V$9,$G18+$H18,0) -> 0 | X18: =IF($C18=X$9,$G18+$H18,0) -> 0 | Y18: =IF($C18=Y$9,$G18+$H18,0) -> 0 | AA18: =IF($C18=AA$9,$G18+$H18,0) -> 0 | AB18: =IF($C18=AB$9,$G18+$H18,0) -> 0 | AC18: =IF($C18=AC$9,$G18+$H18,0) -> 0 | AD18: =IF($C18=AD$9,$G18+$H18,0) -> 0 | AE18: =IF($C18=AE$9,$G18+$H18,0) -> 0 | AF18: =IF($C18=AF$9,$G18+$H18,0) -> 0 | AG18: =IF($C18=AG$9,$G18+$H18,0) -> 0 | AH18: =IF($C18=AH$9,$G18+$H18,0) -> 0 | ... AP18: =IF($C18=AP$9,$G18+$H18,0) -> 0 | AT18: =IF(B18="","",B18) | AU18: =IF(C18="","",$C$5&"-"&A18) | AW18: =IF(AU18="","",COUNTIF(AU:AU,AU18)*2) | AX18: =IF(C18="","",IF($C$4="","",VLOOKUP($C$4,'Chart of Accounts'!$A:$B,2,FALSE))) | AY18: =IF(C18="","",VLOOKUP(C:C,'Chart of Accounts'!$A:$B,2,FALSE)) | AZ18: =IF(C18="","",C18&":"&D18&IF(E18="",""," - "&E18)&IF(F18="",""," - "&F18)) | BA18: =SUM(G18:H18) -> 0 | BB18: =-SUM(G18:H18) -> 0
A19: 2501-008 | I19: =I18+G19+H19 -> 10500 | K19: =SUM(G19:H19)-SUM(L19:AQ19) -> 0 | M19: =IF($C19=M$9,$G19+$H19,0) -> 0 | O19: =IF($C19=O$9,$G19+$H19,0) -> 0 | P19: =IF($C19=P$9,$G19+$H19,0) -> 0 | R19: =IF($C19=R$9,$G19+$H19,0) -> 0 | T19: =IF($C19=T$9,$G19+$H19,0) -> 0 | U19: =IF($C19=U$9,$G19+$H19,0) -> 0 | V19: =IF($C19=V$9,$G19+$H19,0) -> 0 | X19: =IF($C19=X$9,$G19+$H19,0) -> 0 | Y19: =IF($C19=Y$9,$G19+$H19,0) -> 0 | AA19: =IF($C19=AA$9,$G19+$H19,0) -> 0 | AB19: =IF($C19=AB$9,$G19+$H19,0) -> 0 | AC19: =IF($C19=AC$9,$G19+$H19,0) -> 0 | AD19: =IF($C19=AD$9,$G19+$H19,0) -> 0 | AE19: =IF($C19=AE$9,$G19+$H19,0) -> 0 | AF19: =IF($C19=AF$9,$G19+$H19,0) -> 0 | AG19: =IF($C19=AG$9,$G19+$H19,0) -> 0 | AH19: =IF($C19=AH$9,$G19+$H19,0) -> 0 | ... AP19: =IF($C19=AP$9,$G19+$H19,0) -> 0 | AT19: =IF(B19="","",B19) | AU19: =IF(C19="","",$C$5&"-"&A19) | AW19: =IF(AU19="","",COUNTIF(AU:AU,AU19)*2) | AX19: =IF(C19="","",IF($C$4="","",VLOOKUP($C$4,'Chart of Accounts'!$A:$B,2,FALSE))) | AY19: =IF(C19="","",VLOOKUP(C:C,'Chart of Accounts'!$A:$B,2,FALSE)) | AZ19: =IF(C19="","",C19&":"&D19&IF(E19="",""," - "&E19)&IF(F19="",""," - "&F19)) | BA19: =SUM(G19:H19) -> 0 | BB19: =-SUM(G19:H19) -> 0
A20: 2501-009 | I20: =I19+G20+H20 -> 10500 | K20: =SUM(G20:H20)-SUM(L20:AQ20) -> 0 | M20: =IF($C20=M$9,$G20+$H20,0) -> 0 | O20: =IF($C20=O$9,$G20+$H20,0) -> 0 | P20: =IF($C20=P$9,$G20+$H20,0) -> 0 | R20: =IF($C20=R$9,$G20+$H20,0) -> 0 | T20: =IF($C20=T$9,$G20+$H20,0) -> 0 | U20: =IF($C20=U$9,$G20+$H20,0) -> 0 | V20: =IF($C20=V$9,$G20+$H20,0) -> 0 | X20: =IF($C20=X$9,$G20+$H20,0) -> 0 | Y20: =IF($C20=Y$9,$G20+$H20,0) -> 0 | AA20: =IF($C20=AA$9,$G20+$H20,0) -> 0 | AB20: =IF($C20=AB$9,$G20+$H20,0) -> 0 | AC20: =IF($C20=AC$9,$G20+$H20,0) -> 0 | AD20: =IF($C20=AD$9,$G20+$H20,0) -> 0 | AE20: =IF($C20=AE$9,$G20+$H20,0) -> 0 | AF20: =IF($C20=AF$9,$G20+$H20,0) -> 0 | AG20: =IF($C20=AG$9,$G20+$H20,0) -> 0 | AH20: =IF($C20=AH$9,$G20+$H20,0) -> 0 | ... AP20: =IF($C20=AP$9,$G20+$H20,0) -> 0 | AT20: =IF(B20="","",B20) | AU20: =IF(C20="","",$C$5&"-"&A20) | AW20: =IF(AU20="","",COUNTIF(AU:AU,AU20)*2) | AX20: =IF(C20="","",IF($C$4="","",VLOOKUP($C$4,'Chart of Accounts'!$A:$B,2,FALSE))) | AY20: =IF(C20="","",VLOOKUP(C:C,'Chart of Accounts'!$A:$B,2,FALSE)) | AZ20: =IF(C20="","",C20&":"&D20&IF(E20="",""," - "&E20)&IF(F20="",""," - "&F20)) | BA20: =SUM(G20:H20) -> 0 | BB20: =-SUM(G20:H20) -> 0
A21: 2501-010 | I21: =I20+G21+H21 -> 10500 | K21: =SUM(G21:H21)-SUM(L21:AQ21) -> 0 | M21: =IF($C21=M$9,$G21+$H21,0) -> 0 | O21: =IF($C21=O$9,$G21+$H21,0) -> 0 | P21: =IF($C21=P$9,$G21+$H21,0) -> 0 | R21: =IF($C21=R$9,$G21+$H21,0) -> 0 | T21: =IF($C21=T$9,$G21+$H21,0) -> 0 | U21: =IF($C21=U$9,$G21+$H21,0) -> 0 | V21: =IF($C21=V$9,$G21+$H21,0) -> 0 | X21: =IF($C21=X$9,$G21+$H21,0) -> 0 | Y21: =IF($C21=Y$9,$G21+$H21,0) -> 0 | AA21: =IF($C21=AA$9,$G21+$H21,0) -> 0 | AB21: =IF($C21=AB$9,$G21+$H21,0) -> 0 | AC21: =IF($C21=AC$9,$G21+$H21,0) -> 0 | AD21: =IF($C21=AD$9,$G21+$H21,0) -> 0 | AE21: =IF($C21=AE$9,$G21+$H21,0) -> 0 | AF21: =IF($C21=AF$9,$G21+$H21,0) -> 0 | AG21: =IF($C21=AG$9,$G21+$H21,0) -> 0 | AH21: =IF($C21=AH$9,$G21+$H21,0) -> 0 | ... AP21: =IF($C21=AP$9,$G21+$H21,0) -> 0 | AT21: =IF(B21="","",B21) | AU21: =IF(C21="","",$C$5&"-"&A21) | AW21: =IF(AU21="","",COUNTIF(AU:AU,AU21)*2) | AX21: =IF(C21="","",IF($C$4="","",VLOOKUP($C$4,'Chart of Accounts'!$A:$B,2,FALSE))) | AY21: =IF(C21="","",VLOOKUP(C:C,'Chart of Accounts'!$A:$B,2,FALSE)) | AZ21: =IF(C21="","",C21&":"&D21&IF(E21="",""," - "&E21)&IF(F21="",""," - "&F21)) | BA21: =SUM(G21:H21) -> 0 | BB21: =-SUM(G21:H21) -> 0
A22: 2501-011 | I22: =I21+G22+H22 -> 10500 | K22: =SUM(G22:H22)-SUM(L22:AQ22) -> 0 | M22: =IF($C22=M$9,$G22+$H22,0) -> 0 | O22: =IF($C22=O$9,$G22+$H22,0) -> 0 | P22: =IF($C22=P$9,$G22+$H22,0) -> 0 | R22: =IF($C22=R$9,$G22+$H22,0) -> 0 | T22: =IF($C22=T$9,$G22+$H22,0) -> 0 | U22: =IF($C22=U$9,$G22+$H22,0) -> 0 | V22: =IF($C22=V$9,$G22+$H22,0) -> 0 | X22: =IF($C22=X$9,$G22+$H22,0) -> 0 | Y22: =IF($C22=Y$9,$G22+$H22,0) -> 0 | AA22: =IF($C22=AA$9,$G22+$H22,0) -> 0 | AB22: =IF($C22=AB$9,$G22+$H22,0) -> 0 | AC22: =IF($C22=AC$9,$G22+$H22,0) -> 0 | AD22: =IF($C22=AD$9,$G22+$H22,0) -> 0 | AE22: =IF($C22=AE$9,$G22+$H22,0) -> 0 | AF22: =IF($C22=AF$9,$G22+$H22,0) -> 0 | AG22: =IF($C22=AG$9,$G22+$H22,0) -> 0 | AH22: =IF($C22=AH$9,$G22+$H22,0) -> 0 | ... AP22: =IF($C22=AP$9,$G22+$H22,0) -> 0 | AT22: =IF(B22="","",B22) | AU22: =IF(C22="","",$C$5&"-"&A22) | AW22: =IF(AU22="","",COUNTIF(AU:AU,AU22)*2) | AX22: =IF(C22="","",IF($C$4="","",VLOOKUP($C$4,'Chart of Accounts'!$A:$B,2,FALSE))) | AY22: =IF(C22="","",VLOOKUP(C:C,'Chart of Accounts'!$A:$B,2,FALSE)) | AZ22: =IF(C22="","",C22&":"&D22&IF(E22="",""," - "&E22)&IF(F22="",""," - "&F22)) | BA22: =SUM(G22:H22) -> 0 | BB22: =-SUM(G22:H22) -> 0
A23: 2501-012 | I23: =I22+G23+H23 -> 10500 | K23: =SUM(G23:H23)-SUM(L23:AQ23) -> 0 | M23: =IF($C23=M$9,$G23+$H23,0) -> 0 | O23: =IF($C23=O$9,$G23+$H23,0) -> 0 | P23: =IF($C23=P$9,$G23+$H23,0) -> 0 | R23: =IF($C23=R$9,$G23+$H23,0) -> 0 | T23: =IF($C23=T$9,$G23+$H23,0) -> 0 | U23: =IF($C23=U$9,$G23+$H23,0) -> 0 | V23: =IF($C23=V$9,$G23+$H23,0) -> 0 | X23: =IF($C23=X$9,$G23+$H23,0) -> 0 | Y23: =IF($C23=Y$9,$G23+$H23,0) -> 0 | AA23: =IF($C23=AA$9,$G23+$H23,0) -> 0 | AB23: =IF($C23=AB$9,$G23+$H23,0) -> 0 | AC23: =IF($C23=AC$9,$G23+$H23,0) -> 0 | AD23: =IF($C23=AD$9,$G23+$H23,0) -> 0 | AE23: =IF($C23=AE$9,$G23+$H23,0) -> 0 | AF23: =IF($C23=AF$9,$G23+$H23,0) -> 0 | AG23: =IF($C23=AG$9,$G23+$H23,0) -> 0 | AH23: =IF($C23=AH$9,$G23+$H23,0) -> 0 | ... AP23: =IF($C23=AP$9,$G23+$H23,0) -> 0 | AT23: =IF(B23="","",B23) | AU23: =IF(C23="","",$C$5&"-"&A23) | AW23: =IF(AU23="","",COUNTIF(AU:AU,AU23)*2) | AX23: =IF(C23="","",IF($C$4="","",VLOOKUP($C$4,'Chart of Accounts'!$A:$B,2,FALSE))) | AY23: =IF(C23="","",VLOOKUP(C:C,'Chart of Accounts'!$A:$B,2,FALSE)) | AZ23: =IF(C23="","",C23&":"&D23&IF(E23="",""," - "&E23)&IF(F23="",""," - "&F23)) | BA23: =SUM(G23:H23) -> 0 | BB23: =-SUM(G23:H23) -> 0
A24: 2501-013 | I24: =I23+G24+H24 -> 10500 | K24: =SUM(G24:H24)-SUM(L24:AQ24) -> 0 | M24: =IF($C24=M$9,$G24+$H24,0) -> 0 | O24: =IF($C24=O$9,$G24+$H24,0) -> 0 | P24: =IF($C24=P$9,$G24+$H24,0) -> 0 | R24: =IF($C24=R$9,$G24+$H24,0) -> 0 | T24: =IF($C24=T$9,$G24+$H24,0) -> 0 | U24: =IF($C24=U$9,$G24+$H24,0) -> 0 | V24: =IF($C24=V$9,$G24+$H24,0) -> 0 | X24: =IF($C24=X$9,$G24+$H24,0) -> 0 | Y24: =IF($C24=Y$9,$G24+$H24,0) -> 0 | AA24: =IF($C24=AA$9,$G24+$H24,0) -> 0 | AB24: =IF($C24=AB$9,$G24+$H24,0) -> 0 | AC24: =IF($C24=AC$9,$G24+$H24,0) -> 0 | AD24: =IF($C24=AD$9,$G24+$H24,0) -> 0 | AE24: =IF($C24=AE$9,$G24+$H24,0) -> 0 | AF24: =IF($C24=AF$9,$G24+$H24,0) -> 0 | AG24: =IF($C24=AG$9,$G24+$H24,0) -> 0 | AH24: =IF($C24=AH$9,$G24+$H24,0) -> 0 | ... AP24: =IF($C24=AP$9,$G24+$H24,0) -> 0 | AT24: =IF(B24="","",B24) | AU24: =IF(C24="","",$C$5&"-"&A24) | AW24: =IF(AU24="","",COUNTIF(AU:AU,AU24)*2) | AX24: =IF(C24="","",IF($C$4="","",VLOOKUP($C$4,'Chart of Accounts'!$A:$B,2,FALSE))) | AY24: =IF(C24="","",VLOOKUP(C:C,'Chart of Accounts'!$A:$B,2,FALSE)) | AZ24: =IF(C24="","",C24&":"&D24&IF(E24="",""," - "&E24)&IF(F24="",""," - "&F24)) | BA24: =SUM(G24:H24) -> 0 | BB24: =-SUM(G24:H24) -> 0
A25: 2501-014 | I25: =I24+G25+H25 -> 10500 | K25: =SUM(G25:H25)-SUM(L25:AQ25) -> 0 | M25: =IF($C25=M$9,$G25+$H25,0) -> 0 | O25: =IF($C25=O$9,$G25+$H25,0) -> 0 | P25: =IF($C25=P$9,$G25+$H25,0) -> 0 | R25: =IF($C25=R$9,$G25+$H25,0) -> 0 | T25: =IF($C25=T$9,$G25+$H25,0) -> 0 | U25: =IF($C25=U$9,$G25+$H25,0) -> 0 | V25: =IF($C25=V$9,$G25+$H25,0) -> 0 | X25: =IF($C25=X$9,$G25+$H25,0) -> 0 | Y25: =IF($C25=Y$9,$G25+$H25,0) -> 0 | AA25: =IF($C25=AA$9,$G25+$H25,0) -> 0 | AB25: =IF($C25=AB$9,$G25+$H25,0) -> 0 | AC25: =IF($C25=AC$9,$G25+$H25,0) -> 0 | AD25: =IF($C25=AD$9,$G25+$H25,0) -> 0 | AE25: =IF($C25=AE$9,$G25+$H25,0) -> 0 | AF25: =IF($C25=AF$9,$G25+$H25,0) -> 0 | AG25: =IF($C25=AG$9,$G25+$H25,0) -> 0 | AH25: =IF($C25=AH$9,$G25+$H25,0) -> 0 | ... AP25: =IF($C25=AP$9,$G25+$H25,0) -> 0 | AT25: =IF(B25="","",B25) | AU25: =IF(C25="","",$C$5&"-"&A25) | AW25: =IF(AU25="","",COUNTIF(AU:AU,AU25)*2) | AX25: =IF(C25="","",IF($C$4="","",VLOOKUP($C$4,'Chart of Accounts'!$A:$B,2,FALSE))) | AY25: =IF(C25="","",VLOOKUP(C:C,'Chart of Accounts'!$A:$B,2,FALSE)) | AZ25: =IF(C25="","",C25&":"&D25&IF(E25="",""," - "&E25)&IF(F25="",""," - "&F25)) | BA25: =SUM(G25:H25) -> 0 | BB25: =-SUM(G25:H25) -> 0
... A102: 2501-091 | I102: =I101+G102+H102 -> 10500 | K102: =SUM(G102:H102)-SUM(L102:AQ102) -> 0 | M102: =IF($C102=M$9,$G102+$H102,0) -> 0 | O102: =IF($C102=O$9,$G102+$H102,0) -> 0 | P102: =IF($C102=P$9,$G102+$H102,0) -> 0 | R102: =IF($C102=R$9,$G102+$H102,0) -> 0 | T102: =IF($C102=T$9,$G102+$H102,0) -> 0 | U102: =IF($C102=U$9,$G102+$H102,0) -> 0 | V102: =IF($C102=V$9,$G102+$H102,0) -> 0 | X102: =IF($C102=X$9,$G102+$H102,0) -> 0 | Y102: =IF($C102=Y$9,$G102+$H102,0) -> 0 | AA102: =IF($C102=AA$9,$G102+$H102,0) -> 0 | AB102: =IF($C102=AB$9,$G102+$H102,0) -> 0 | AC102: =IF($C102=AC$9,$G102+$H102,0) -> 0 | AD102: =IF($C102=AD$9,$G102+$H102,0) -> 0 | AE102: =IF($C102=AE$9,$G102+$H102,0) -> 0 | AF102: =IF($C102=AF$9,$G102+$H102,0) -> 0 | AG102: =IF($C102=AG$9,$G102+$H102,0) -> 0 | AH102: =IF($C102=AH$9,$G102+$H102,0) -> 0 | ... AP102: =IF($C102=AP$9,$G102+$H102,0) -> 0 | AT102: =IF(B102="","",B102) | AU102: =IF(C102="","",$C$5&"-"&A102) | AW102: =IF(AU102="","",COUNTIF(AU:AU,AU102)*2) | AX102: =IF(C102="","",IF($C$4="","",VLOOKUP($C$4,'Chart of Accounts'!$A:$B,2,FALSE))) | AY102: =IF(C102="","",VLOOKUP(C:C,'Chart of Accounts'!$A:$B,2,FALSE)) | AZ102: =IF(C102="","",C102&":"&D102&IF(E102="",""," - "&E102)&IF(F102="",""," - "&F102)) | BA102: =SUM(G102:H102) -> 0 | BB102: =-SUM(G102:H102) -> 0
G104: =SUBTOTAL(9,G11:G103) -> 1000 | H104: =SUBTOTAL(9,H11:H103) -> -500 | M104: =SUBTOTAL(9,M11:M103) -> 0 | O104: =SUBTOTAL(9,O11:O103) -> 0 | P104: =SUBTOTAL(9,P11:P103) -> 0 | R104: =SUBTOTAL(9,R11:R103) -> 0 | T104: =SUBTOTAL(9,T11:T103) -> 0 | U104: =SUBTOTAL(9,U11:U103) -> 0 | V104: =SUBTOTAL(9,V11:V103) -> 0 | X104: =SUBTOTAL(9,X11:X103) -> 1000 | Y104: =SUBTOTAL(9,Y11:Y103) -> 0 | AA104: =SUBTOTAL(9,AA11:AA103) -> 0 | AB104: =SUBTOTAL(9,AB11:AB103) -> 0 | AC104: =SUBTOTAL(9,AC11:AC103) -> 0 | AD104: =SUBTOTAL(9,AD11:AD103) -> 0 | AE104: =SUBTOTAL(9,AE11:AE103) -> 0 | AF104: =SUBTOTAL(9,AF11:AF103) -> 0 | AG104: =SUBTOTAL(9,AG11:AG103) -> 0 | AH104: =SUBTOTAL(9,AH11:AH103) -> 0 | ... AP104: =SUBTOTAL(9,AP11:AP103) -> 0 | BA104: =SUBTOTAL(9,BA11:BA103) -> 500 | BB104: =SUBTOTAL(9,BB11:BB103) -> -500

Sheet Credit Card
A1: Company Name | C1: ABC Ltd | G1: Remind | I1: - "+ve" for income, "-ve" for expenses
A2: Period | C2: 1.1.25-31.12.25
A3: Credit Card record | C3: HSBC Credit Card #1234-5678-9123-4567
A4: Card COA: | C4: HSBC HKD Credit Card
A5: Reference name: | C5: CrCard:001
BF8: For Peachtree import use
B9: Date | C9: Particular | I9: Cash in | J9: Cash out | K9: Balance | M9: Control | O9: Interbank | Q9: Computer equipment | R9: Fixture & furniture | T9: Director's C/A | V9: Trade receivable | W9: Trade payable | X9: Accruals | Z9: Sales | AA9: Purchases | AC9: Bank interest income | AE9: Director's remuneration | AF9: Salaries | AG9: Mandatory provident fund | AI9: Advertisement | AJ9: Bank charges | AK9: Business registration fee | AL9: Company secretary fee | AM9: Electricity & water | AN9: Entertainment | AO9: Insurance | AP9: Legal and professional fee | AQ9: Local travelling | AR9: Postage & courier | AS9: Printing & stationery | AT9: Rental expenses | AU9: Staff welfare | AV9: Stamp duty | AW9: Telecommunication | AX9: Transportation | BB9: Date | BC9: Reference | BE9: Number of Distributions | BF9: G/L Account (Bank) | BG9: G/L Account (Nature) | BH9: Description | BI9: Bank (Amount$) | BJ9: Nature (Amount$)
A10: No. | B10: Date | C10: Nature | D10: Payer / (Payee) | E10: Invoice no. (Cheque no.) | F10: Details | G10: Month-Year | BF10: Please don't move this column
A11: 0 | B11: 45658 | C11: Cash opening | K11: 10000
A12: 2501-001 | B12: 45658 | C12: Sales | D12: Sale invoce #12345 | F12: ABC customer | G12: 45658 | I12: 1000 | K12: =K11+I12+J12 -> 11000 | M12: =SUM(I12:J12)-SUM(N12:AY12) -> 0 | O12: =IF($C12=O$9,$I12+$J12,0) -> 0 | Q12: =IF($C12=Q$9,$I12+$J12,0) -> 0 | R12: =IF($C12=R$9,$I12+$J12,0) -> 0 | T12: =IF($C12=T$9,$I12+$J12,0) -> 0 | V12: =IF($C12=V$9,$I12+$J12,0) -> 0 | W12: =IF($C12=W$9,$I12+$J12,0) -> 0 | X12: =IF($C12=X$9,$I12+$J12,0) -> 0 | Z12: =IF($C12=Z$9,$I12+$J12,0) -> 1000 | AA12: =IF($C12=AA$9,$I12+$J12,0) -> 0 | AC12: =IF($C12=AC$9,$I12+$J12,0) -> 0 | AE12: =IF($C12=AE$9,$I12+$J12,0) -> 0 | AF12: =IF($C12=AF$9,$I12+$J12,0) -> 0 | AG12: =IF($C12=AG$9,$I12+$J12,0) -> 0 | AI12: =IF($C12=AI$9,$I12+$J12,0) -> 0 | AJ12: =IF($C12=AJ$9,$I12+$J12,0) -> 0 | AK12: =IF($C12=AK$9,$I12+$J12,0) -> 0 | AL12: =IF($C12=AL$9,$I12+$J12,0) -> 0 | AM12: =IF($C12=AM$9,$I12+$J12,0) -> 0 | AN12: =IF($C12=AN$9,$I12+$J12,0) -> 0 | AO12: =IF($C12=AO$9,$I12+$J12,0) -> 0 | AP12: =IF($C12=AP$9,$I12+$J12,0) -> 0 | ... AX12: =IF($C12=AX$9,$I12+$J12,0) -> 0 | BB12: =IF(B12="","",B12) -> 45658 | BC12: =IF(C12="","",$C$5&"-"&A12) -> CrCard:001-2501-001 | BE12: =IF(BC12="","",COUNTIF(BC:BC,BC12)*2) -> 2 | BF12: =IF(C12="","",IF($C$4="","",VLOOKUP($C$4,'Chart of Accounts'!$A:$B,2,FALSE))) -> 1080 | BG12: =IF(C12="","",VLOOKUP(C:C,'Chart of Accounts'!$A:$B,2,FALSE)) -> 4000 | BH12: =IF(C12="","",C12&":"&D12&IF(E12="",""," - "&E12)&IF(F12="",""," - "&F12)&IF(G12="",""," - "&TEXT(G12,"MMM-YY"))) -> Sales:Sale invoce #12345 - ABC customer - Jan-25 | BI12: =SUM(I12:J12) -> 1000 | BJ12: =-SUM(I12:J12) -> -1000
A13: 2501-002 | B13: 45658 | C13: Local travelling | D13: Travelling | J13: -500 | K13: =K12+I13+J13 -> 10500 | M13: =SUM(I13:J13)-SUM(N13:AY13) -> 0 | O13: =IF($C13=O$9,$I13+$J13,0) -> 0 | Q13: =IF($C13=Q$9,$I13+$J13,0) -> 0 | R13: =IF($C13=R$9,$I13+$J13,0) -> 0 | T13: =IF($C13=T$9,$I13+$J13,0) -> 0 | V13: =IF($C13=V$9,$I13+$J13,0) -> 0 | W13: =IF($C13=W$9,$I13+$J13,0) -> 0 | X13: =IF($C13=X$9,$I13+$J13,0) -> 0 | Z13: =IF($C13=Z$9,$I13+$J13,0) -> 0 | AA13: =IF($C13=AA$9,$I13+$J13,0) -> 0 | AC13: =IF($C13=AC$9,$I13+$J13,0) -> 0 | AE13: =IF($C13=AE$9,$I13+$J13,0) -> 0 | AF13: =IF($C13=AF$9,$I13+$J13,0) -> 0 | AG13: =IF($C13=AG$9,$I13+$J13,0) -> 0 | AI13: =IF($C13=AI$9,$I13+$J13,0) -> 0 | AJ13: =IF($C13=AJ$9,$I13+$J13,0) -> 0 | AK13: =IF($C13=AK$9,$I13+$J13,0) -> 0 | AL13: =IF($C13=AL$9,$I13+$J13,0) -> 0 | AM13: =IF($C13=AM$9,$I13+$J13,0) -> 0 | AN13: =IF($C13=AN$9,$I13+$J13,0) -> 0 | AO13: =IF($C13=AO$9,$I13+$J13,0) -> 0 | AP13: =IF($C13=AP$9,$I13+$J13,0) -> 0 | ... AX13: =IF($C13=AX$9,$I13+$J13,0) -> 0 | BB13: =IF(B13="","",B13) -> 45658 | BC13: =IF(C13="","",$C$5&"-"&A13) -> CrCard:001-2501-002 | BE13: =IF(BC13="","",COUNTIF(BC:BC,BC13)*2) -> 2 | BF13: =IF(C13="","",IF($C$4="","",VLOOKUP($C$4,'Chart of Accounts'!$A:$B,2,FALSE))) -> 1080 | BG13: =IF(C13="","",VLOOKUP(C:C,'Chart of Accounts'!$A:$B,2,FALSE)) -> 6750 | BH13: =IF(C13="","",C13&":"&D13&IF(E13="",""," - "&E13)&IF(F13="",""," - "&F13)&IF(G13="",""," - "&TEXT(G13,"MMM-YY"))) -> Local travelling:Travelling | BI13: =SUM(I13:J13) -> -500 | BJ13: =-SUM(I13:J13) -> 500
A14: 2501-003 | K14: =K13+I14+J14 -> 10500 | M14: =SUM(I14:J14)-SUM(N14:AY14) -> 0 | O14: =IF($C14=O$9,$I14+$J14,0) -> 0 | Q14: =IF($C14=Q$9,$I14+$J14,0) -> 0 | R14: =IF($C14=R$9,$I14+$J14,0) -> 0 | T14: =IF($C14=T$9,$I14+$J14,0) -> 0 | V14: =IF($C14=V$9,$I14+$J14,0) -> 0 | W14: =IF($C14=W$9,$I14+$J14,0) -> 0 | X14: =IF($C14=X$9,$I14+$J14,0) -> 0 | Z14: =IF($C14=Z$9,$I14+$J14,0) -> 0 | AA14: =IF($C14=AA$9,$I14+$J14,0) -> 0 | AC14: =IF($C14=AC$9,$I14+$J14,0) -> 0 | AE14: =IF($C14=AE$9,$I14+$J14,0) -> 0 | AF14: =IF($C14=AF$9,$I14+$J14,0) -> 0 | AG14: =IF($C14=AG$9,$I14+$J14,0) -> 0 | AI14: =IF($C14=AI$9,$I14+$J14,0) -> 0 | AJ14: =IF($C14=AJ$9,$I14+$J14,0) -> 0 | AK14: =IF($C14=AK$9,$I14+$J14,0) -> 0 | AL14: =IF($C14=AL$9,$I14+$J14,0) -> 0 | AM14: =IF($C14=AM$9,$I14+$J14,0) -> 0 | AN14: =IF($C14=AN$9,$I14+$J14,0) -> 0 | AO14: =IF($C14=AO$9,$I14+$J14,0) -> 0 | AP14: =IF($C14=AP$9,$I14+$J14,0) -> 0 | ... AX14: =IF($C14=AX$9,$I14+$J14,0) -> 0 | BB14: =IF(B14="","",B14) | BC14: =IF(C14="","",$C$5&"-"&A14) | BE14: =IF(BC14="","",COUNTIF(BC:BC,BC14)*2) | BF14: =IF(C14="","",IF($C$4="","",VLOOKUP($C$4,'Chart of Accounts'!$A:$B,2,FALSE))) | BG14: =IF(C14="","",VLOOKUP(C:C,'Chart of Accounts'!$A:$B,2,FALSE)) | BH14: =IF(C14="","",C14&":"&D14&IF(E14="",""," - "&E14)&IF(F14="",""," - "&F14)&IF(G14="",""," - "&TEXT(G14,"MMM-YY"))) | BI14: =SUM(I14:J14) -> 0 | BJ14: =-SUM(I14:J14) -> 0
A15: 2501-004 | K15: =K14+I15+J15 -> 10500 | M15: =SUM(I15:J15)-SUM(N15:AY15) -> 0 | O15: =IF($C15=O$9,$I15+$J15,0) -> 0 | Q15: =IF($C15=Q$9,$I15+$J15,0) -> 0 | R15: =IF($C15=R$9,$I15+$J15,0) -> 0 | T15: =IF($C15=T$9,$I15+$J15,0) -> 0 | V15: =IF($C15=V$9,$I15+$J15,0) -> 0 | W15: =IF($C15=W$9,$I15+$J15,0) -> 0 | X15: =IF($C15=X$9,$I15+$J15,0) -> 0 | Z15: =IF($C15=Z$9,$I15+$J15,0) -> 0 | AA15: =IF($C15=AA$9,$I15+$J15,0) -> 0 | AC15: =IF($C15=AC$9,$I15+$J15,0) -> 0 | AE15: =IF($C15=AE$9,$I15+$J15,0) -> 0 | AF15: =IF($C15=AF$9,$I15+$J15,0) -> 0 | AG15: =IF($C15=AG$9,$I15+$J15,0) -> 0 | AI15: =IF($C15=AI$9,$I15+$J15,0) -> 0 | AJ15: =IF($C15=AJ$9,$I15+$J15,0) -> 0 | AK15: =IF($C15=AK$9,$I15+$J15,0) -> 0 | AL15: =IF($C15=AL$9,$I15+$J15,0) -> 0 | AM15: =IF($C15=AM$9,$I15+$J15,0) -> 0 | AN15: =IF($C15=AN$9,$I15+$J15,0) -> 0 | AO15: =IF($C15=AO$9,$I15+$J15,0) -> 0 | AP15: =IF($C15=AP$9,$I15+$J15,0) -> 0 | ... AX15: =IF($C15=AX$9,$I15+$J15,0) -> 0 | BB15: =IF(B15="","",B15) | BC15: =IF(C15="","",$C$5&"-"&A15) | BE15: =IF(BC15="","",COUNTIF(BC:BC,BC15)*2) | BF15: =IF(C15="","",IF($C$4="","",VLOOKUP($C$4,'Chart of Accounts'!$A:$B,2,FALSE))) | BG15: =IF(C15="","",VLOOKUP(C:C,'Chart of Accounts'!$A:$B,2,FALSE)) | BH15: =IF(C15="","",C15&":"&D15&IF(E15="",""," - "&E15)&IF(F15="",""," - "&F15)&IF(G15="",""," - "&TEXT(G15,"MMM-YY"))) | BI15: =SUM(I15:J15) -> 0 | BJ15: =-SUM(I15:J15) -> 0
A16: 2501-005 | K16: =K15+I16+J16 -> 10500 | M16: =SUM(I16:J16)-SUM(N16:AY16) -> 0 | O16: =IF($C16=O$9,$I16+$J16,0) -> 0 | Q16: =IF($C16=Q$9,$I16+$J16,0) -> 0 | R16: =IF($C16=R$9,$I16+$J16,0) -> 0 | T16: =IF($C16=T$9,$I16+$J16,0) -> 0 | V16: =IF($C16=V$9,$I16+$J16,0) -> 0 | W16: =IF($C16=W$9,$I16+$J16,0) -> 0 | X16: =IF($C16=X$9,$I16+$J16,0) -> 0 | Z16: =IF($C16=Z$9,$I16+$J16,0) -> 0 | AA16: =IF($C16=AA$9,$I16+$J16,0) -> 0 | AC16: =IF($C16=AC$9,$I16+$J16,0) -> 0 | AE16: =IF($C16=AE$9,$I16+$J16,0) -> 0 | AF16: =IF($C16=AF$9,$I16+$J16,0) -> 0 | AG16: =IF($C16=AG$9,$I16+$J16,0) -> 0 | AI16: =IF($C16=AI$9,$I16+$J16,0) -> 0 | AJ16: =IF($C16=AJ$9,$I16+$J16,0) -> 0 | AK16: =IF($C16=AK$9,$I16+$J16,0) -> 0 | AL16: =IF($C16=AL$9,$I16+$J16,0) -> 0 | AM16: =IF($C16=AM$9,$I16+$J16,0) -> 0 | AN16: =IF($C16=AN$9,$I16+$J16,0) -> 0 | AO16: =IF($C16=AO$9,$I16+$J16,0) -> 0 | AP16: =IF($C16=AP$9,$I16+$J16,0) -> 0 | ... AX16: =IF($C16=AX$9,$I16+$J16,0) -> 0 | BB16: =IF(B16="","",B16) | BC16: =IF(C16="","",$C$5&"-"&A16) | BE16: =IF(BC16="","",COUNTIF(BC:BC,BC16)*2) | BF16: =IF(C16="","",IF($C$4="","",VLOOKUP($C$4,'Chart of Accounts'!$A:$B,2,FALSE))) | BG16: =IF(C16="","",VLOOKUP(C:C,'Chart of Accounts'!$A:$B,2,FALSE)) | BH16: =IF(C16="","",C16&":"&D16&IF(E16="",""," - "&E16)&IF(F16="",""," - "&F16)&IF(G16="",""," - "&TEXT(G16,"MMM-YY"))) | BI16: =SUM(I16:J16) -> 0 | BJ16: =-SUM(I16:J16) -> 0
A17: 2501-006 | K17: =K16+I17+J17 -> 10500 | M17: =SUM(I17:J17)-SUM(N17:AY17) -> 0 | O17: =IF($C17=O$9,$I17+$J17,0) -> 0 | Q17: =IF($C17=Q$9,$I17+$J17,0) -> 0 | R17: =IF($C17=R$9,$I17+$J17,0) -> 0 | T17: =IF($C17=T$9,$I17+$J17,0) -> 0 | V17: =IF($C17=V$9,$I17+$J17,0) -> 0 | W17: =IF($C17=W$9,$I17+$J17,0) -> 0 | X17: =IF($C17=X$9,$I17+$J17,0) -> 0 | Z17: =IF($C17=Z$9,$I17+$J17,0) -> 0 | AA17: =IF($C17=AA$9,$I17+$J17,0) -> 0 | AC17: =IF($C17=AC$9,$I17+$J17,0) -> 0 | AE17: =IF($C17=AE$9,$I17+$J17,0) -> 0 | AF17: =IF($C17=AF$9,$I17+$J17,0) -> 0 | AG17: =IF($C17=AG$9,$I17+$J17,0) -> 0 | AI17: =IF($C17=AI$9,$I17+$J17,0) -> 0 | AJ17: =IF($C17=AJ$9,$I17+$J17,0) -> 0 | AK17: =IF($C17=AK$9,$I17+$J17,0) -> 0 | AL17: =IF($C17=AL$9,$I17+$J17,0) -> 0 | AM17: =IF($C17=AM$9,$I17+$J17,0) -> 0 | AN17: =IF($C17=AN$9,$I17+$J17,0) -> 0 | AO17: =IF($C17=AO$9,$I17+$J17,0) -> 0 | AP17: =IF($C17=AP$9,$I17+$J17,0) -> 0 | ... AX17: =IF($C17=AX$9,$I17+$J17,0) -> 0 | BB17: =IF(B17="","",B17) | BC17: =IF(C17="","",$C$5&"-"&A17) | BE17: =IF(BC17="","",COUNTIF(BC:BC,BC17)*2) | BF17: =IF(C17="","",IF($C$4="","",VLOOKUP($C$4,'Chart of Accounts'!$A:$B,2,FALSE))) | BG17: =IF(C17="","",VLOOKUP(C:C,'Chart of Accounts'!$A:$B,2,FALSE)) | BH17: =IF(C17="","",C17&":"&D17&IF(E17="",""," - "&E17)&IF(F17="",""," - "&F17)&IF(G17="",""," - "&TEXT(G17,"MMM-YY"))) | BI17: =SUM(I17:J17) -> 0 | BJ17: =-SUM(I17:J17) -> 0
A18: 2501-007 | K18: =K17+I18+J18 -> 10500 | M18: =SUM(I18:J18)-SUM(N18:AY18) -> 0 | O18: =IF($C18=O$9,$I18+$J18,0) -> 0 | Q18: =IF($C18=Q$9,$I18+$J18,0) -> 0 | R18: =IF($C18=R$9,$I18+$J18,0) -> 0 | T18: =IF($C18=T$9,$I18+$J18,0) -> 0 | V18: =IF($C18=V$9,$I18+$J18,0) -> 0 | W18: =IF($C18=W$9,$I18+$J18,0) -> 0 | X18: =IF($C18=X$9,$I18+$J18,0) -> 0 | Z18: =IF($C18=Z$9,$I18+$J18,0) -> 0 | AA18: =IF($C18=AA$9,$I18+$J18,0) -> 0 | AC18: =IF($C18=AC$9,$I18+$J18,0) -> 0 | AE18: =IF($C18=AE$9,$I18+$J18,0) -> 0 | AF18: =IF($C18=AF$9,$I18+$J18,0) -> 0 | AG18: =IF($C18=AG$9,$I18+$J18,0) -> 0 | AI18: =IF($C18=AI$9,$I18+$J18,0) -> 0 | AJ18: =IF($C18=AJ$9,$I18+$J18,0) -> 0 | AK18: =IF($C18=AK$9,$I18+$J18,0) -> 0 | AL18: =IF($C18=AL$9,$I18+$J18,0) -> 0 | AM18: =IF($C18=AM$9,$I18+$J18,0) -> 0 | AN18: =IF($C18=AN$9,$I18+$J18,0) -> 0 | AO18: =IF($C18=AO$9,$I18+$J18,0) -> 0 | AP18: =IF($C18=AP$9,$I18+$J18,0) -> 0 | ... AX18: =IF($C18=AX$9,$I18+$J18,0) -> 0 | BB18: =IF(B18="","",B18) | BC18: =IF(C18="","",$C$5&"-"&A18) | BE18: =IF(BC18="","",COUNTIF(BC:BC,BC18)*2) | BF18: =IF(C18="","",IF($C$4="","",VLOOKUP($C$4,'Chart of Accounts'!$A:$B,2,FALSE))) | BG18: =IF(C18="","",VLOOKUP(C:C,'Chart of Accounts'!$A:$B,2,FALSE)) | BH18: =IF(C18="","",C18&":"&D18&IF(E18="",""," - "&E18)&IF(F18="",""," - "&F18)&IF(G18="",""," - "&TEXT(G18,"MMM-YY"))) | BI18: =SUM(I18:J18) -> 0 | BJ18: =-SUM(I18:J18) -> 0
A19: 2501-008 | K19: =K18+I19+J19 -> 10500 | M19: =SUM(I19:J19)-SUM(N19:AY19) -> 0 | O19: =IF($C19=O$9,$I19+$J19,0) -> 0 | Q19: =IF($C19=Q$9,$I19+$J19,0) -> 0 | R19: =IF($C19=R$9,$I19+$J19,0) -> 0 | T19: =IF($C19=T$9,$I19+$J19,0) -> 0 | V19: =IF($C19=V$9,$I19+$J19,0) -> 0 | W19: =IF($C19=W$9,$I19+$J19,0) -> 0 | X19: =IF($C19=X$9,$I19+$J19,0) -> 0 | Z19: =IF($C19=Z$9,$I19+$J19,0) -> 0 | AA19: =IF($C19=AA$9,$I19+$J19,0) -> 0 | AC19: =IF($C19=AC$9,$I19+$J19,0) -> 0 | AE19: =IF($C19=AE$9,$I19+$J19,0) -> 0 | AF19: =IF($C19=AF$9,$I19+$J19,0) -> 0 | AG19: =IF($C19=AG$9,$I19+$J19,0) -> 0 | AI19: =IF($C19=AI$9,$I19+$J19,0) -> 0 | AJ19: =IF($C19=AJ$9,$I19+$J19,0) -> 0 | AK19: =IF($C19=AK$9,$I19+$J19,0) -> 0 | AL19: =IF($C19=AL$9,$I19+$J19,0) -> 0 | AM19: =IF($C19=AM$9,$I19+$J19,0) -> 0 | AN19: =IF($C19=AN$9,$I19+$J19,0) -> 0 | AO19: =IF($C19=AO$9,$I19+$J19,0) -> 0 | AP19: =IF($C19=AP$9,$I19+$J19,0) -> 0 | ... AX19: =IF($C19=AX$9,$I19+$J19,0) -> 0 | BB19: =IF(B19="","",B19) | BC19: =IF(C19="","",$C$5&"-"&A19) | BE19: =IF(BC19="","",COUNTIF(BC:BC,BC19)*2) | BF19: =IF(C19="","",IF($C$4="","",VLOOKUP($C$4,'Chart of Accounts'!$A:$B,2,FALSE))) | BG19: =IF(C19="","",VLOOKUP(C:C,'Chart of Accounts'!$A:$B,2,FALSE)) | BH19: =IF(C19="","",C19&":"&D19&IF(E19="",""," - "&E19)&IF(F19="",""," - "&F19)&IF(G19="",""," - "&TEXT(G19,"MMM-YY"))) | BI19: =SUM(I19:J19) -> 0 | BJ19: =-SUM(I19:J19) -> 0
A20: 2501-009 | K20: =K19+I20+J20 -> 10500 | M20: =SUM(I20:J20)-SUM(N20:AY20) -> 0 | O20: =IF($C20=O$9,$I20+$J20,0) -> 0 | Q20: =IF($C20=Q$9,$I20+$J20,0) -> 0 | R20: =IF($C20=R$9,$I20+$J20,0) -> 0 | T20: =IF($C20=T$9,$I20+$J20,0) -> 0 | V20: =IF($C20=V$9,$I20+$J20,0) -> 0 | W20: =IF($C20=W$9,$I20+$J20,0) -> 0 | X20: =IF($C20=X$9,$I20+$J20,0) -> 0 | Z20: =IF($C20=Z$9,$I20+$J20,0) -> 0 | AA20: =IF($C20=AA$9,$I20+$J20,0) -> 0 | AC20: =IF($C20=AC$9,$I20+$J20,0) -> 0 | AE20: =IF($C20=AE$9,$I20+$J20,0) -> 0 | AF20: =IF($C20=AF$9,$I20+$J20,0) -> 0 | AG20: =IF($C20=AG$9,$I20+$J20,0) -> 0 | AI20: =IF($C20=AI$9,$I20+$J20,0) -> 0 | AJ20: =IF($C20=AJ$9,$I20+$J20,0) -> 0 | AK20: =IF($C20=AK$9,$I20+$J20,0) -> 0 | AL20: =IF($C20=AL$9,$I20+$J20,0) -> 0 | AM20: =IF($C20=AM$9,$I20+$J20,0) -> 0 | AN20: =IF($C20=AN$9,$I20+$J20,0) -> 0 | AO20: =IF($C20=AO$9,$I20+$J20,0) -> 0 | AP20: =IF($C20=AP$9,$I20+$J20,0) -> 0 | ... AX20: =IF($C20=AX$9,$I20+$J20,0) -> 0 | BB20: =IF(B20="","",B20) | BC20: =IF(C20="","",$C$5&"-"&A20) | BE20: =IF(BC20="","",COUNTIF(BC:BC,BC20)*2) | BF20: =IF(C20="","",IF($C$4="","",VLOOKUP($C$4,'Chart of Accounts'!$A:$B,2,FALSE))) | BG20: =IF(C20="","",VLOOKUP(C:C,'Chart of Accounts'!$A:$B,2,FALSE)) | BH20: =IF(C20="","",C20&":"&D20&IF(E20="",""," - "&E20)&IF(F20="",""," - "&F20)&IF(G20="",""," - "&TEXT(G20,"MMM-YY"))) | BI20: =SUM(I20:J20) -> 0 | BJ20: =-SUM(I20:J20) -> 0
A21: 2501-010 | K21: =K20+I21+J21 -> 10500 | M21: =SUM(I21:J21)-SUM(N21:AY21) -> 0 | O21: =IF($C21=O$9,$I21+$J21,0) -> 0 | Q21: =IF($C21=Q$9,$I21+$J21,0) -> 0 | R21: =IF($C21=R$9,$I21+$J21,0) -> 0 | T21: =IF($C21=T$9,$I21+$J21,0) -> 0 | V21: =IF($C21=V$9,$I21+$J21,0) -> 0 | W21: =IF($C21=W$9,$I21+$J21,0) -> 0 | X21: =IF($C21=X$9,$I21+$J21,0) -> 0 | Z21: =IF($C21=Z$9,$I21+$J21,0) -> 0 | AA21: =IF($C21=AA$9,$I21+$J21,0) -> 0 | AC21: =IF($C21=AC$9,$I21+$J21,0) -> 0 | AE21: =IF($C21=AE$9,$I21+$J21,0) -> 0 | AF21: =IF($C21=AF$9,$I21+$J21,0) -> 0 | AG21: =IF($C21=AG$9,$I21+$J21,0) -> 0 | AI21: =IF($C21=AI$9,$I21+$J21,0) -> 0 | AJ21: =IF($C21=AJ$9,$I21+$J21,0) -> 0 | AK21: =IF($C21=AK$9,$I21+$J21,0) -> 0 | AL21: =IF($C21=AL$9,$I21+$J21,0) -> 0 | AM21: =IF($C21=AM$9,$I21+$J21,0) -> 0 | AN21: =IF($C21=AN$9,$I21+$J21,0) -> 0 | AO21: =IF($C21=AO$9,$I21+$J21,0) -> 0 | AP21: =IF($C21=AP$9,$I21+$J21,0) -> 0 | ... AX21: =IF($C21=AX$9,$I21+$J21,0) -> 0 | BB21: =IF(B21="","",B21) | BC21: =IF(C21="","",$C$5&"-"&A21) | BE21: =IF(BC21="","",COUNTIF(BC:BC,BC21)*2) | BF21: =IF(C21="","",IF($C$4="","",VLOOKUP($C$4,'Chart of Accounts'!$A:$B,2,FALSE))) | BG21: =IF(C21="","",VLOOKUP(C:C,'Chart of Accounts'!$A:$B,2,FALSE)) | BH21: =IF(C21="","",C21&":"&D21&IF(E21="",""," - "&E21)&IF(F21="",""," - "&F21)&IF(G21="",""," - "&TEXT(G21,"MMM-YY"))) | BI21: =SUM(I21:J21) -> 0 | BJ21: =-SUM(I21:J21) -> 0
A22: 2501-011 | K22: =K21+I22+J22 -> 10500 | M22: =SUM(I22:J22)-SUM(N22:AY22) -> 0 | O22: =IF($C22=O$9,$I22+$J22,0) -> 0 | Q22: =IF($C22=Q$9,$I22+$J22,0) -> 0 | R22: =IF($C22=R$9,$I22+$J22,0) -> 0 | T22: =IF($C22=T$9,$I22+$J22,0) -> 0 | V22: =IF($C22=V$9,$I22+$J22,0) -> 0 | W22: =IF($C22=W$9,$I22+$J22,0) -> 0 | X22: =IF($C22=X$9,$I22+$J22,0) -> 0 | Z22: =IF($C22=Z$9,$I22+$J22,0) -> 0 | AA22: =IF($C22=AA$9,$I22+$J22,0) -> 0 | AC22: =IF($C22=AC$9,$I22+$J22,0) -> 0 | AE22: =IF($C22=AE$9,$I22+$J22,0) -> 0 | AF22: =IF($C22=AF$9,$I22+$J22,0) -> 0 | AG22: =IF($C22=AG$9,$I22+$J22,0) -> 0 | AI22: =IF($C22=AI$9,$I22+$J22,0) -> 0 | AJ22: =IF($C22=AJ$9,$I22+$J22,0) -> 0 | AK22: =IF($C22=AK$9,$I22+$J22,0) -> 0 | AL22: =IF($C22=AL$9,$I22+$J22,0) -> 0 | AM22: =IF($C22=AM$9,$I22+$J22,0) -> 0 | AN22: =IF($C22=AN$9,$I22+$J22,0) -> 0 | AO22: =IF($C22=AO$9,$I22+$J22,0) -> 0 | AP22: =IF($C22=AP$9,$I22+$J22,0) -> 0 | ... AX22: =IF($C22=AX$9,$I22+$J22,0) -> 0 | BB22: =IF(B22="","",B22) | BC22: =IF(C22="","",$C$5&"-"&A22) | BE22: =IF(BC22="","",COUNTIF(BC:BC,BC22)*2) | BF22: =IF(C22="","",IF($C$4="","",VLOOKUP($C$4,'Chart of Accounts'!$A:$B,2,FALSE))) | BG22: =IF(C22="","",VLOOKUP(C:C,'Chart of Accounts'!$A:$B,2,FALSE)) | BH22: =IF(C22="","",C22&":"&D22&IF(E22="",""," - "&E22)&IF(F22="",""," - "&F22)&IF(G22="",""," - "&TEXT(G22,"MMM-YY"))) | BI22: =SUM(I22:J22) -> 0 | BJ22: =-SUM(I22:J22) -> 0
A23: 2501-012 | K23: =K22+I23+J23 -> 10500 | M23: =SUM(I23:J23)-SUM(N23:AY23) -> 0 | O23: =IF($C23=O$9,$I23+$J23,0) -> 0 | Q23: =IF($C23=Q$9,$I23+$J23,0) -> 0 | R23: =IF($C23=R$9,$I23+$J23,0) -> 0 | T23: =IF($C23=T$9,$I23+$J23,0) -> 0 | V23: =IF($C23=V$9,$I23+$J23,0) -> 0 | W23: =IF($C23=W$9,$I23+$J23,0) -> 0 | X23: =IF($C23=X$9,$I23+$J23,0) -> 0 | Z23: =IF($C23=Z$9,$I23+$J23,0) -> 0 | AA23: =IF($C23=AA$9,$I23+$J23,0) -> 0 | AC23: =IF($C23=AC$9,$I23+$J23,0) -> 0 | AE23: =IF($C23=AE$9,$I23+$J23,0) -> 0 | AF23: =IF($C23=AF$9,$I23+$J23,0) -> 0 | AG23: =IF($C23=AG$9,$I23+$J23,0) -> 0 | AI23: =IF($C23=AI$9,$I23+$J23,0) -> 0 | AJ23: =IF($C23=AJ$9,$I23+$J23,0) -> 0 | AK23: =IF($C23=AK$9,$I23+$J23,0) -> 0 | AL23: =IF($C23=AL$9,$I23+$J23,0) -> 0 | AM23: =IF($C23=AM$9,$I23+$J23,0) -> 0 | AN23: =IF($C23=AN$9,$I23+$J23,0) -> 0 | AO23: =IF($C23=AO$9,$I23+$J23,0) -> 0 | AP23: =IF($C23=AP$9,$I23+$J23,0) -> 0 | ... AX23: =IF($C23=AX$9,$I23+$J23,0) -> 0 | BB23: =IF(B23="","",B23) | BC23: =IF(C23="","",$C$5&"-"&A23) | BE23: =IF(BC23="","",COUNTIF(BC:BC,BC23)*2) | BF23: =IF(C23="","",IF($C$4="","",VLOOKUP($C$4,'Chart of Accounts'!$A:$B,2,FALSE))) | BG23: =IF(C23="","",VLOOKUP(C:C,'Chart of Accounts'!$A:$B,2,FALSE)) | BH23: =IF(C23="","",C23&":"&D23&IF(E23="",""," - "&E23)&IF(F23="",""," - "&F23)&IF(G23="",""," - "&TEXT(G23,"MMM-YY"))) | BI23: =SUM(I23:J23) -> 0 | BJ23: =-SUM(I23:J23) -> 0
A24: 2501-013 | K24: =K23+I24+J24 -> 10500 | M24: =SUM(I24:J24)-SUM(N24:AY24) -> 0 | O24: =IF($C24=O$9,$I24+$J24,0) -> 0 | Q24: =IF($C24=Q$9,$I24+$J24,0) -> 0 | R24: =IF($C24=R$9,$I24+$J24,0) -> 0 | T24: =IF($C24=T$9,$I24+$J24,0) -> 0 | V24: =IF($C24=V$9,$I24+$J24,0) -> 0 | W24: =IF($C24=W$9,$I24+$J24,0) -> 0 | X24: =IF($C24=X$9,$I24+$J24,0) -> 0 | Z24: =IF($C24=Z$9,$I24+$J24,0) -> 0 | AA24: =IF($C24=AA$9,$I24+$J24,0) -> 0 | AC24: =IF($C24=AC$9,$I24+$J24,0) -> 0 | AE24: =IF($C24=AE$9,$I24+$J24,0) -> 0 | AF24: =IF($C24=AF$9,$I24+$J24,0) -> 0 | AG24: =IF($C24=AG$9,$I24+$J24,0) -> 0 | AI24: =IF($C24=AI$9,$I24+$J24,0) -> 0 | AJ24: =IF($C24=AJ$9,$I24+$J24,0) -> 0 | AK24: =IF($C24=AK$9,$I24+$J24,0) -> 0 | AL24: =IF($C24=AL$9,$I24+$J24,0) -> 0 | AM24: =IF($C24=AM$9,$I24+$J24,0) -> 0 | AN24: =IF($C24=AN$9,$I24+$J24,0) -> 0 | AO24: =IF($C24=AO$9,$I24+$J24,0) -> 0 | AP24: =IF($C24=AP$9,$I24+$J24,0) -> 0 | ... AX24: =IF($C24=AX$9,$I24+$J24,0) -> 0 | BB24: =IF(B24="","",B24) | BC24: =IF(C24="","",$C$5&"-"&A24) | BE24: =IF(BC24="","",COUNTIF(BC:BC,BC24)*2) | BF24: =IF(C24="","",IF($C$4="","",VLOOKUP($C$4,'Chart of Accounts'!$A:$B,2,FALSE))) | BG24: =IF(C24="","",VLOOKUP(C:C,'Chart of Accounts'!$A:$B,2,FALSE)) | BH24: =IF(C24="","",C24&":"&D24&IF(E24="",""," - "&E24)&IF(F24="",""," - "&F24)&IF(G24="",""," - "&TEXT(G24,"MMM-YY"))) | BI24: =SUM(I24:J24) -> 0 | BJ24: =-SUM(I24:J24) -> 0
A25: 2501-014 | K25: =K24+I25+J25 -> 10500 | M25: =SUM(I25:J25)-SUM(N25:AY25) -> 0 | O25: =IF($C25=O$9,$I25+$J25,0) -> 0 | Q25: =IF($C25=Q$9,$I25+$J25,0) -> 0 | R25: =IF($C25=R$9,$I25+$J25,0) -> 0 | T25: =IF($C25=T$9,$I25+$J25,0) -> 0 | V25: =IF($C25=V$9,$I25+$J25,0) -> 0 | W25: =IF($C25=W$9,$I25+$J25,0) -> 0 | X25: =IF($C25=X$9,$I25+$J25,0) -> 0 | Z25: =IF($C25=Z$9,$I25+$J25,0) -> 0 | AA25: =IF($C25=AA$9,$I25+$J25,0) -> 0 | AC25: =IF($C25=AC$9,$I25+$J25,0) -> 0 | AE25: =IF($C25=AE$9,$I25+$J25,0) -> 0 | AF25: =IF($C25=AF$9,$I25+$J25,0) -> 0 | AG25: =IF($C25=AG$9,$I25+$J25,0) -> 0 | AI25: =IF($C25=AI$9,$I25+$J25,0) -> 0 | AJ25: =IF($C25=AJ$9,$I25+$J25,0) -> 0 | AK25: =IF($C25=AK$9,$I25+$J25,0) -> 0 | AL25: =IF($C25=AL$9,$I25+$J25,0) -> 0 | AM25: =IF($C25=AM$9,$I25+$J25,0) -> 0 | AN25: =IF($C25=AN$9,$I25+$J25,0) -> 0 | AO25: =IF($C25=AO$9,$I25+$J25,0) -> 0 | AP25: =IF($C25=AP$9,$I25+$J25,0) -> 0 | ... AX25: =IF($C25=AX$9,$I25+$J25,0) -> 0 | BB25: =IF(B25="","",B25) | BC25: =IF(C25="","",$C$5&"-"&A25) | BE25: =IF(BC25="","",COUNTIF(BC:BC,BC25)*2) | BF25: =IF(C25="","",IF($C$4="","",VLOOKUP($C$4,'Chart of Accounts'!$A:$B,2,FALSE))) | BG25: =IF(C25="","",VLOOKUP(C:C,'Chart of Accounts'!$A:$B,2,FALSE)) | BH25: =IF(C25="","",C25&":"&D25&IF(E25="",""," - "&E25)&IF(F25="",""," - "&F25)&IF(G25="",""," - "&TEXT(G25,"MMM-YY"))) | BI25: =SUM(I25:J25) -> 0 | BJ25: =-SUM(I25:J25) -> 0
... A102: 2501-091 | K102: =K101+I102+J102 -> 10500 | M102: =SUM(I102:J102)-SUM(N102:AY102) -> 0 | O102: =IF($C102=O$9,$I102+$J102,0) -> 0 | Q102: =IF($C102=Q$9,$I102+$J102,0) -> 0 | R102: =IF($C102=R$9,$I102+$J102,0) -> 0 | T102: =IF($C102=T$9,$I102+$J102,0) -> 0 | V102: =IF($C102=V$9,$I102+$J102,0) -> 0 | W102: =IF($C102=W$9,$I102+$J102,0) -> 0 | X102: =IF($C102=X$9,$I102+$J102,0) -> 0 | Z102: =IF($C102=Z$9,$I102+$J102,0) -> 0 | AA102: =IF($C102=AA$9,$I102+$J102,0) -> 0 | AC102: =IF($C102=AC$9,$I102+$J102,0) -> 0 | AE102: =IF($C102=AE$9,$I102+$J102,0) -> 0 | AF102: =IF($C102=AF$9,$I102+$J102,0) -> 0 | AG102: =IF($C102=AG$9,$I102+$J102,0) -> 0 | AI102: =IF($C102=AI$9,$I102+$J102,0) -> 0 | AJ102: =IF($C102=AJ$9,$I102+$J102,0) -> 0 | AK102: =IF($C102=AK$9,$I102+$J102,0) -> 0 | AL102: =IF($C102=AL$9,$I102+$J102,0) -> 0 | AM102: =IF($C102=AM$9,$I102+$J102,0) -> 0 | AN102: =IF($C102=AN$9,$I102+$J102,0) -> 0 | AO102: =IF($C102=AO$9,$I102+$J102,0) -> 0 | AP102: =IF($C102=AP$9,$I102+$J102,0) -> 0 | ... AX102: =IF($C102=AX$9,$I102+$J102,0) -> 0 | BB102: =IF(B102="","",B102) | BC102: =IF(C102="","",$C$5&"-"&A102) | BE102: =IF(BC102="","",COUNTIF(BC:BC,BC102)*2) | BF102: =IF(C102="","",IF($C$4="","",VLOOKUP($C$4,'Chart of Accounts'!$A:$B,2,FALSE))) | BG102: =IF(C102="","",VLOOKUP(C:C,'Chart of Accounts'!$A:$B,2,FALSE)) | BH102: =IF(C102="","",C102&":"&D102&IF(E102="",""," - "&E102)&IF(F102="",""," - "&F102)&IF(G102="",""," - "&TEXT(G102,"MMM-YY"))) | BI102: =SUM(I102:J102) -> 0 | BJ102: =-SUM(I102:J102) -> 0
I104: =SUBTOTAL(9,I11:I103) -> 1000 | J104: =SUBTOTAL(9,J11:J103) -> -500 | M104: =SUM(I104:J104)-SUM(N104:AY104) -> 0 | O104: =SUBTOTAL(9,O11:O103) -> 0 | Q104: =SUBTOTAL(9,Q11:Q103) -> 0 | R104: =SUBTOTAL(9,R11:R103) -> 0 | T104: =SUBTOTAL(9,T11:T103) -> 0 | V104: =SUBTOTAL(9,V11:V103) -> 0 | W104: =SUBTOTAL(9,W11:W103) -> 0 | X104: =SUBTOTAL(9,X11:X103) -> 0 | Z104: =SUBTOTAL(9,Z11:Z103) -> 1000 | AA104: =SUBTOTAL(9,AA11:AA103) -> 0 | AC104: =SUBTOTAL(9,AC11:AC103) -> 0 | AE104: =SUBTOTAL(9,AE11:AE103) -> 0 | AF104: =SUBTOTAL(9,AF11:AF103) -> 0 | AG104: =SUBTOTAL(9,AG11:AG103) -> 0 | AI104: =SUBTOTAL(9,AI11:AI103) -> 0 | AJ104: =SUBTOTAL(9,AJ11:AJ103) -> 0 | AK104: =SUBTOTAL(9,AK11:AK103) -> 0 | AL104: =SUBTOTAL(9,AL11:AL103) -> 0 | AM104: =SUBTOTAL(9,AM11:AM103) -> 0 | AN104: =SUBTOTAL(9,AN11:AN103) -> 0 | AO104: =SUBTOTAL(9,AO11:AO103) -> 0 | AP104: =SUBTOTAL(9,AP11:AP103) -> 0 | ... AX104: =SUBTOTAL(9,AX11:AX103) -> 0 | BI104: =SUBTOTAL(9,BI11:BI103) -> 500 | BJ104: =SUBTOTAL(9,BJ11:BJ103) -> -500

Sheet Chart of Accounts
A1: Account Description | B1: Account ID
A2: Cash | B2: 1000
A3: HSB HKD CA | B3: 1010
A4: HSB HKD SA | B4: 1020
A5: BOC HKD CA | B5: 1030
A6: BOC HKD SA | B6: 1040
A7: HSBC USD CA | B7: 1050
A8: HSBC USD SA | B8: 1060
A9: HSBC HKD Credit Card | B9: 1080
A10: Interbank | B10: 1090
A11: Temp | B11: 1099
A12: Trade receivable | B12: 1100
A13: Other receivables | B13: 1120
... A107: Income tax expenses | B107: 9000
