Workbook

Sheet HSBC HKD CA
A1: Company Name | C1: Hesen (Hong Kong) Trading Limited | G1: Remind | H1: - "+ve" for income, "-ve" for expenses
A2: Period | C2: 1.1.25-31.12.25 | H2: - 1 file for each bank account
A3: Bank record | C3: HSBC HKD CA #121-891824-001
A4: Bank COA: | C4: HSBC HKD CA
A5: Bank name: | C5: HSBC HKD CA
AB8: For Peachtree import use - Please don't move this column
A9: No. | B9: Date | C9: Particular | I9: Deposit | J9: Withdrawal | K9: Balance | M9: Control | O9: Interbank | Q9: Accruals | S9: Bank interest income | U9: Bank charges | V9: Business registration fee | W9: Company secretarial fee | X9: Temp | AB9: Date | AC9: Reference | AE9: Number of Distributions | AF9: G/L Account (Bank) | AG9: G/L Account (Nature) | AH9: Description | AI9: Bank (Amount$) | AJ9: Nature (Amount$)
A10: No. | B10: Date | C10: Nature | D10: Payer / (Payee) | E10: Invoice no. (Cheque no.) | F10: Details | G10: Month-Year
A11: 0 | B11: 45658 | C11: Bank opening | K11: 17954.38
A12: 2501-001 | B12: 45814 | C12: Bank charges | D12: CHARGES | J12: -5 | K12: =K11+I12+J12 -> 17949.38 | M12: =SUM(I12:J12)-SUM(N12:Y12) -> 0 | O12: =IF($C12=O$9,$I12+$J12,0) -> 0 | Q12: =IF($C12=Q$9,$I12+$J12,0) -> 0 | S12: =IF($C12=S$9,$I12+$J12,0) -> 0 | U12: =IF($C12=U$9,$I12+$J12,0) -> -5 | V12: =IF($C12=V$9,$I12+$J12,0) -> 0 | W12: =IF($C12=W$9,$I12+$J12,0) -> 0 | X12: =IF($C12=X$9,$I12+$J12,0) -> 0 | AB12: =IF(B12="","",B12) -> 45814 | AC12: =IF(C12="","",$C$5&"-"&A12) -> HSBC HKD CA-2501-001 | AE12: =IF(AC12="","",COUNTIF(AC:AC,AC12)*2) -> 2 | AF12: =IF(C12="","",IF($C$4="","",VLOOKUP($C$4,'Chart of Accounts'!$A:$B,2,FALSE))) -> 1030 | AG12: =IF(C12="","",VLOOKUP(C:C,'Chart of Accounts'!$A:$B,2,FALSE)) -> 6200 | AH12: =IF(C12="","",C12&":"&D12&IF(E12="",""," - "&E12)&IF(F12="",""," - "&F12)&IF(G12="",""," - "&TEXT(G12,"MMM-YY"))) -> Bank charges:CHARGES | AI12: =SUM(I12:J12) -> -5 | AJ12: =-AI12 -> 5
A13: 2501-002 | B13: 45814 | C13: Accruals | D13: DENNIS MAK CPA LIMITED | J13: -6200 | K13: =K12+I13+J13 -> 11749.38 | M13: =SUM(I13:J13)-SUM(N13:Y13) -> 0 | O13: =IF($C13=O$9,$I13+$J13,0) -> 0 | Q13: =IF($C13=Q$9,$I13+$J13,0) -> -6200 | S13: =IF($C13=S$9,$I13+$J13,0) -> 0 | U13: =IF($C13=U$9,$I13+$J13,0) -> 0 | V13: =IF($C13=V$9,$I13+$J13,0) -> 0 | W13: =IF($C13=W$9,$I13+$J13,0) -> 0 | X13: =IF($C13=X$9,$I13+$J13,0) -> 0 | AB13: =IF(B13="","",B13) -> 45814 | AC13: =IF(C13="","",$C$5&"-"&A13) -> HSBC HKD CA-2501-002 | AE13: =IF(AC13="","",COUNTIF(AC:AC,AC13)*2) -> 2 | AF13: =IF(C13="","",IF($C$4="","",VLOOKUP($C$4,'Chart of Accounts'!$A:$B,2,FALSE))) -> 1030 | AG13: =IF(C13="","",VLOOKUP(C:C,'Chart of Accounts'!$A:$B,2,FALSE)) -> 2200 | AH13: =IF(C13="","",C13&":"&D13&IF(E13="",""," - "&E13)&IF(F13="",""," - "&F13)&IF(G13="",""," - "&TEXT(G13,"MMM-YY"))) -> Accruals:DENNIS MAK CPA LIMITED | AI13: =SUM(I13:J13) -> -6200 | AJ13: =-AI13 -> 6200
A14: 2501-003 | B14: 45814 | C14: Bank charges | D14: CHARGES | J14: -5 | K14: =K13+I14+J14 -> 11744.38 | M14: =SUM(I14:J14)-SUM(N14:Y14) -> 0 | O14: =IF($C14=O$9,$I14+$J14,0) -> 0 | Q14: =IF($C14=Q$9,$I14+$J14,0) -> 0 | S14: =IF($C14=S$9,$I14+$J14,0) -> 0 | U14: =IF($C14=U$9,$I14+$J14,0) -> -5 | V14: =IF($C14=V$9,$I14+$J14,0) -> 0 | W14: =IF($C14=W$9,$I14+$J14,0) -> 0 | X14: =IF($C14=X$9,$I14+$J14,0) -> 0 | AB14: =IF(B14="","",B14) -> 45814 | AC14: =IF(C14="","",$C$5&"-"&A14) -> HSBC HKD CA-2501-003 | AE14: =IF(AC14="","",COUNTIF(AC:AC,AC14)*2) -> 2 | AF14: =IF(C14="","",IF($C$4="","",VLOOKUP($C$4,'Chart of Accounts'!$A:$B,2,FALSE))) -> 1030 | AG14: =IF(C14="","",VLOOKUP(C:C,'Chart of Accounts'!$A:$B,2,FALSE)) -> 6200 | AH14: =IF(C14="","",C14&":"&D14&IF(E14="",""," - "&E14)&IF(F14="",""," - "&F14)&IF(G14="",""," - "&TEXT(G14,"MMM-YY"))) -> Bank charges:CHARGES | AI14: =SUM(I14:J14) -> -5 | AJ14: =-AI14 -> 5
A15: 2501-004 | B15: 45814 | C15: Accruals | D15: DM SECRETARY LIMITED | J15: -4000 | K15: =K14+I15+J15 -> 7744.38 | M15: =SUM(I15:J15)-SUM(N15:Y15) -> 0 | O15: =IF($C15=O$9,$I15+$J15,0) -> 0 | Q15: =IF($C15=Q$9,$I15+$J15,0) -> -4000 | S15: =IF($C15=S$9,$I15+$J15,0) -> 0 | U15: =IF($C15=U$9,$I15+$J15,0) -> 0 | V15: =IF($C15=V$9,$I15+$J15,0) -> 0 | W15: =IF($C15=W$9,$I15+$J15,0) -> 0 | X15: =IF($C15=X$9,$I15+$J15,0) -> 0 | AB15: =IF(B15="","",B15) -> 45814 | AC15: =IF(C15="","",$C$5&"-"&A15) -> HSBC HKD CA-2501-004 | AE15: =IF(AC15="","",COUNTIF(AC:AC,AC15)*2) -> 2 | AF15: =IF(C15="","",IF($C$4="","",VLOOKUP($C$4,'Chart of Accounts'!$A:$B,2,FALSE))) -> 1030 | AG15: =IF(C15="","",VLOOKUP(C:C,'Chart of Accounts'!$A:$B,2,FALSE)) -> 2200 | AH15: =IF(C15="","",C15&":"&D15&IF(E15="",""," - "&E15)&IF(F15="",""," - "&F15)&IF(G15="",""," - "&TEXT(G15,"MMM-YY"))) -> Accruals:DM SECRETARY LIMITED | AI15: =SUM(I15:J15) -> -4000 | AJ15: =-AI15 -> 4000
A16: 2501-005 | B16: 45849 | C16: Company secretarial fee | D16: DM SECRETARY LIMITED | J16: =-7305+2200 -> -5105 | K16: =K14+I16+J16 -> 6639.38 | M16: =SUM(I16:J16)-SUM(N16:Y16) -> 0 | O16: =IF($C16=O$9,$I16+$J16,0) -> 0 | Q16: =IF($C16=Q$9,$I16+$J16,0) -> 0 | S16: =IF($C16=S$9,$I16+$J16,0) -> 0 | U16: =IF($C16=U$9,$I16+$J16,0) -> 0 | V16: =IF($C16=V$9,$I16+$J16,0) -> 0 | W16: =IF($C16=W$9,$I16+$J16,0) -> -5105 | X16: =IF($C16=X$9,$I16+$J16,0) -> 0 | AB16: =IF(B16="","",B16) -> 45849 | AC16: =IF(C16="","",$C$5&"-"&A16) -> HSBC HKD CA-2501-005 | AE16: =IF(AC16="","",COUNTIF(AC:AC,AC16)*2) -> 4 | AF16: =IF(C16="","",IF($C$4="","",VLOOKUP($C$4,'Chart of Accounts'!$A:$B,2,FALSE))) -> 1030 | AG16: =IF(C16="","",VLOOKUP(C:C,'Chart of Accounts'!$A:$B,2,FALSE)) -> 6300 | AH16: =IF(C16="","",C16&":"&D16&IF(E16="",""," - "&E16)&IF(F16="",""," - "&F16)&IF(G16="",""," - "&TEXT(G16,"MMM-YY"))) -> Company secretarial fee:DM SECRETARY LIMITED | AI16: =SUM(I16:J16) -> -5105 | AJ16: =-AI16 -> 5105
A17: 2501-005 | B17: 45849 | C17: Business registration fee | D17: DM SECRETARY LIMITED | J17: =-7305+5105 -> -2200 | K17: =K15+I17+J17 -> 5544.38 | M17: =SUM(I17:J17)-SUM(N17:Y17) -> 0 | O17: =IF($C17=O$9,$I17+$J17,0) -> 0 | Q17: =IF($C17=Q$9,$I17+$J17,0) -> 0 | S17: =IF($C17=S$9,$I17+$J17,0) -> 0 | U17: =IF($C17=U$9,$I17+$J17,0) -> 0 | V17: =IF($C17=V$9,$I17+$J17,0) -> -2200 | W17: =IF($C17=W$9,$I17+$J17,0) -> 0 | X17: =IF($C17=X$9,$I17+$J17,0) -> 0 | AB17: =IF(B17="","",B17) -> 45849 | AC17: =IF(C17="","",$C$5&"-"&A17) -> HSBC HKD CA-2501-005 | AE17: =IF(AC17="","",COUNTIF(AC:AC,AC17)*2) -> 4 | AF17: =IF(C17="","",IF($C$4="","",VLOOKUP($C$4,'Chart of Accounts'!$A:$B,2,FALSE))) -> 1030 | AG17: =IF(C17="","",VLOOKUP(C:C,'Chart of Accounts'!$A:$B,2,FALSE)) -> 6250 | AH17: =IF(C17="","",C17&":"&D17&IF(E17="",""," - "&E17)&IF(F17="",""," - "&F17)&IF(G17="",""," - "&TEXT(G17,"MMM-YY"))) -> Business registration fee:DM SECRETARY LIMITED | AI17: =SUM(I17:J17) -> -2200 | AJ17: =-AI17 -> 2200
A18: 2501-006 | B18: 45849 | C18: Bank charges | D18: CHARGES | J18: -5 | K18: =K17+I18+J18 -> 5539.38 | M18: =SUM(I18:J18)-SUM(N18:Y18) -> 0 | O18: =IF($C18=O$9,$I18+$J18,0) -> 0 | Q18: =IF($C18=Q$9,$I18+$J18,0) -> 0 | S18: =IF($C18=S$9,$I18+$J18,0) -> 0 | U18: =IF($C18=U$9,$I18+$J18,0) -> -5 | V18: =IF($C18=V$9,$I18+$J18,0) -> 0 | W18: =IF($C18=W$9,$I18+$J18,0) -> 0 | X18: =IF($C18=X$9,$I18+$J18,0) -> 0 | AB18: =IF(B18="","",B18) -> 45849 | AC18: =IF(C18="","",$C$5&"-"&A18) -> HSBC HKD CA-2501-006 | AE18: =IF(AC18="","",COUNTIF(AC:AC,AC18)*2) -> 2 | AF18: =IF(C18="","",IF($C$4="","",VLOOKUP($C$4,'Chart of Accounts'!$A:$B,2,FALSE))) -> 1030 | AG18: =IF(C18="","",VLOOKUP(C:C,'Chart of Accounts'!$A:$B,2,FALSE)) -> 6200 | AH18: =IF(C18="","",C18&":"&D18&IF(E18="",""," - "&E18)&IF(F18="",""," - "&F18)&IF(G18="",""," - "&TEXT(G18,"MMM-YY"))) -> Bank charges:CHARGES | AI18: =SUM(I18:J18) -> -5 | AJ18: =-AI18 -> 5
I20: =SUBTOTAL(9,I11:I19) -> 0 | J20: =SUBTOTAL(9,J11:J19) -> -17520 | M20: =SUM(I20:J20)-SUM(N20:W20) -> 0 | O20: =SUBTOTAL(9,O11:O19) -> 0 | Q20: =SUBTOTAL(9,Q11:Q19) -> -10200 | S20: =SUBTOTAL(9,S11:S19) -> 0 | U20: =SUBTOTAL(9,U11:U19) -> -15 | V20: =SUBTOTAL(9,V11:V19) -> -2200 | W20: =SUBTOTAL(9,W11:W19) -> -5105 | X20: =SUBTOTAL(9,X11:X19) -> 0 | AI20: =SUBTOTAL(9,AI11:AI19) -> -17520 | AJ20: =SUBTOTAL(9,AJ11:AJ19) -> 17520
AJ21: =SUM(AI20:AJ20) -> 0

Sheet HSBC HKD SA
A1: Company Name | C1: Hesen (Hong Kong) Trading Limited | G1: Remind | H1: - "+ve" for income, "-ve" for expenses
A2: Period | C2: 1.1.25-31.12.25 | H2: - 1 file for each bank account
A3: Bank record | C3: HSBC HKD CA #121-891824-838
A4: Bank COA (Peachtree): | C4: HSBC HKD SA
A5: Bank name: | C5: HSBC HKD SA
BD8: For Peachtree import use - Please don't move this column
A9: No. | B9: Date | C9: Particular | I9: Deposit | J9: Withdrawal | K9: Balance | M9: Control | O9: Interbank | Q9: Computer equipment | R9: Fixture & furniture | T9: Director's C/A | V9: Trade receivable | W9: Trade payable | X9: Accruals | Z9: Sales | AA9: Purchases | AC9: Bank interest income | AE9: Director's remuneration | AF9: Salaries | AG9: Mandatory provident fund | AI9: Advertisement | AJ9: Bank charges | AK9: Business registration fee | AL9: Company secretary fee | AM9: Exchange losses/(gains), net | AN9: Entertainment | AO9: Insurance | AP9: Legal and professional fee | AQ9: Local travelling | AR9: Postage & courier | AS9: Printing & stationery | AT9: Rental expenses | AU9: Staff welfare | AV9: Stamp duty | AW9: Telecommunication | AX9: Transportation | AZ9: Temp | BD9: Date | BE9: Reference | BG9: Number of Distributions | BH9: G/L Account (Bank) | BI9: G/L Account (Nature) | BJ9: Description | BK9: Bank (Amount$) | BL9: Nature (Amount$)
A10: No. | B10: Date | C10: Nature | D10: Payer / (Payee) | E10: Invoice no. (Cheque no.) | F10: Details | G10: Month-Year
A11: 0 | B11: 45658 | C11: Bank opening | K11: 3237.62
A12: 2501-001 | B12: 45716 | C12: Bank interest income | D12: CREDIT INTEREST | I12: 0.01 | K12: =K11+I12+J12 -> 3237.63 | M12: =SUM(I12:J12)-SUM(N12:BA12) -> 0 | O12: =IF($C12=O$9,$I12+$J12,0) -> 0 | Q12: =IF($C12=Q$9,$I12+$J12,0) -> 0 | R12: =IF($C12=R$9,$I12+$J12,0) -> 0 | T12: =IF($C12=T$9,$I12+$J12,0) -> 0 | V12: =IF($C12=V$9,$I12+$J12,0) -> 0 | W12: =IF($C12=W$9,$I12+$J12,0) -> 0 | X12: =IF($C12=X$9,$I12+$J12,0) -> 0 | Z12: =IF($C12=Z$9,$I12+$J12,0) -> 0 | AA12: =IF($C12=AA$9,$I12+$J12,0) -> 0 | AC12: =IF($C12=AC$9,$I12+$J12,0) -> 0.01 | AE12: =IF($C12=AE$9,$I12+$J12,0) -> 0 | AF12: =IF($C12=AF$9,$I12+$J12,0) -> 0 | AG12: =IF($C12=AG$9,$I12+$J12,0) -> 0 | AI12: =IF($C12=AI$9,$I12+$J12,0) -> 0 | AJ12: =IF($C12=AJ$9,$I12+$J12,0) -> 0 | AK12: =IF($C12=AK$9,$I12+$J12,0) -> 0 | AL12: =IF($C12=AL$9,$I12+$J12,0) -> 0 | AM12: =IF($C12=AM$9,$I12+$J12,0) -> 0 | AN12: =IF($C12=AN$9,$I12+$J12,0) -> 0 | AO12: =IF($C12=AO$9,$I12+$J12,0) -> 0 | AP12: =IF($C12=AP$9,$I12+$J12,0) -> 0 | ... AX12: =IF($C12=AX$9,$I12+$J12,0) -> 0 | AZ12: =IF($C12=AZ$9,$I12+$J12,0) -> 0 | BD12: =IF(B12="","",B12) -> 45716 | BE12: =IF(C12="","",$C$5&"-"&A12) -> HSBC HKD SA-2501-001 | BG12: =IF(BE12="","",COUNTIF(BE:BE,BE12)*2) -> 2 | BH12: =IF(C12="","",IF($C$4="","",VLOOKUP($C$4,'Chart of Accounts'!$A:$B,2,FALSE))) -> 1020 | BI12: =IF(C12="","",VLOOKUP(C:C,'Chart of Accounts'!$A:$B,2,FALSE)) -> 4100 | BJ12: =IF(C12="","",C12&":"&D12&IF(E12="",""," - "&E12)&IF(F12="",""," - "&F12)&IF(G12="",""," - "&TEXT(G12,"MMM-YY"))) -> Bank interest income:CREDIT INTEREST | BK12: =SUM(I12:J12) -> 0.01 | BL12: =-BK12 -> -0.01
A13: 2501-002 | B13: 45790 | C13: Bank charges | D13: CHG FOR AUDIT CONF O | J13: -760 | K13: =K12+I13+J13 -> 2477.63 | M13: =SUM(I13:J13)-SUM(N13:BA13) -> 0 | O13: =IF($C13=O$9,$I13+$J13,0) -> 0 | Q13: =IF($C13=Q$9,$I13+$J13,0) -> 0 | R13: =IF($C13=R$9,$I13+$J13,0) -> 0 | T13: =IF($C13=T$9,$I13+$J13,0) -> 0 | V13: =IF($C13=V$9,$I13+$J13,0) -> 0 | W13: =IF($C13=W$9,$I13+$J13,0) -> 0 | X13: =IF($C13=X$9,$I13+$J13,0) -> 0 | Z13: =IF($C13=Z$9,$I13+$J13,0) -> 0 | AA13: =IF($C13=AA$9,$I13+$J13,0) -> 0 | AC13: =IF($C13=AC$9,$I13+$J13,0) -> 0 | AE13: =IF($C13=AE$9,$I13+$J13,0) -> 0 | AF13: =IF($C13=AF$9,$I13+$J13,0) -> 0 | AG13: =IF($C13=AG$9,$I13+$J13,0) -> 0 | AI13: =IF($C13=AI$9,$I13+$J13,0) -> 0 | AJ13: =IF($C13=AJ$9,$I13+$J13,0) -> -760 | AK13: =IF($C13=AK$9,$I13+$J13,0) -> 0 | AL13: =IF($C13=AL$9,$I13+$J13,0) -> 0 | AM13: =IF($C13=AM$9,$I13+$J13,0) -> 0 | AN13: =IF($C13=AN$9,$I13+$J13,0) -> 0 | AO13: =IF($C13=AO$9,$I13+$J13,0) -> 0 | AP13: =IF($C13=AP$9,$I13+$J13,0) -> 0 | ... AX13: =IF($C13=AX$9,$I13+$J13,0) -> 0 | AZ13: =IF($C13=AZ$9,$I13+$J13,0) -> 0 | BD13: =IF(B13="","",B13) -> 45790 | BE13: =IF(C13="","",$C$5&"-"&A13) -> HSBC HKD SA-2501-002 | BG13: =IF(BE13="","",COUNTIF(BE:BE,BE13)*2) -> 2 | BH13: =IF(C13="","",IF($C$4="","",VLOOKUP($C$4,'Chart of Accounts'!$A:$B,2,FALSE))) -> 1020 | BI13: =IF(C13="","",VLOOKUP(C:C,'Chart of Accounts'!$A:$B,2,FALSE)) -> 6200 | BJ13: =IF(C13="","",C13&":"&D13&IF(E13="",""," - "&E13)&IF(F13="",""," - "&F13)&IF(G13="",""," - "&TEXT(G13,"MMM-YY"))) -> Bank charges:CHG FOR AUDIT CONF O | BK13: =SUM(I13:J13) -> -760 | BL13: =-BK13 -> 760
A14: 2501-003 | B14: 45807 | C14: Bank charges | D14: ACCT MAINT FEE | J14: -150 | K14: =K13+I14+J14 -> 2327.63 | M14: =SUM(I14:J14)-SUM(N14:BA14) -> 0 | O14: =IF($C14=O$9,$I14+$J14,0) -> 0 | Q14: =IF($C14=Q$9,$I14+$J14,0) -> 0 | R14: =IF($C14=R$9,$I14+$J14,0) -> 0 | T14: =IF($C14=T$9,$I14+$J14,0) -> 0 | V14: =IF($C14=V$9,$I14+$J14,0) -> 0 | W14: =IF($C14=W$9,$I14+$J14,0) -> 0 | X14: =IF($C14=X$9,$I14+$J14,0) -> 0 | Z14: =IF($C14=Z$9,$I14+$J14,0) -> 0 | AA14: =IF($C14=AA$9,$I14+$J14,0) -> 0 | AC14: =IF($C14=AC$9,$I14+$J14,0) -> 0 | AE14: =IF($C14=AE$9,$I14+$J14,0) -> 0 | AF14: =IF($C14=AF$9,$I14+$J14,0) -> 0 | AG14: =IF($C14=AG$9,$I14+$J14,0) -> 0 | AI14: =IF($C14=AI$9,$I14+$J14,0) -> 0 | AJ14: =IF($C14=AJ$9,$I14+$J14,0) -> -150 | AK14: =IF($C14=AK$9,$I14+$J14,0) -> 0 | AL14: =IF($C14=AL$9,$I14+$J14,0) -> 0 | AM14: =IF($C14=AM$9,$I14+$J14,0) -> 0 | AN14: =IF($C14=AN$9,$I14+$J14,0) -> 0 | AO14: =IF($C14=AO$9,$I14+$J14,0) -> 0 | AP14: =IF($C14=AP$9,$I14+$J14,0) -> 0 | ... AX14: =IF($C14=AX$9,$I14+$J14,0) -> 0 | AZ14: =IF($C14=AZ$9,$I14+$J14,0) -> 0 | BD14: =IF(B14="","",B14) -> 45807 | BE14: =IF(C14="","",$C$5&"-"&A14) -> HSBC HKD SA-2501-003 | BG14: =IF(BE14="","",COUNTIF(BE:BE,BE14)*2) -> 2 | BH14: =IF(C14="","",IF($C$4="","",VLOOKUP($C$4,'Chart of Accounts'!$A:$B,2,FALSE))) -> 1020 | BI14: =IF(C14="","",VLOOKUP(C:C,'Chart of Accounts'!$A:$B,2,FALSE)) -> 6200 | BJ14: =IF(C14="","",C14&":"&D14&IF(E14="",""," - "&E14)&IF(F14="",""," - "&F14)&IF(G14="",""," - "&TEXT(G14,"MMM-YY"))) -> Bank charges:ACCT MAINT FEE | BK14: =SUM(I14:J14) -> -150 | BL14: =-BK14 -> 150
A15: 2501-004 | B15: 45836 | C15: Bank interest income | D15: CREDIT INTEREST | I15: 0.01 | K15: =K14+I15+J15 -> 2327.64 | M15: =SUM(I15:J15)-SUM(N15:BA15) -> 0 | O15: =IF($C15=O$9,$I15+$J15,0) -> 0 | Q15: =IF($C15=Q$9,$I15+$J15,0) -> 0 | R15: =IF($C15=R$9,$I15+$J15,0) -> 0 | T15: =IF($C15=T$9,$I15+$J15,0) -> 0 | V15: =IF($C15=V$9,$I15+$J15,0) -> 0 | W15: =IF($C15=W$9,$I15+$J15,0) -> 0 | X15: =IF($C15=X$9,$I15+$J15,0) -> 0 | Z15: =IF($C15=Z$9,$I15+$J15,0) -> 0 | AA15: =IF($C15=AA$9,$I15+$J15,0) -> 0 | AC15: =IF($C15=AC$9,$I15+$J15,0) -> 0.01 | AE15: =IF($C15=AE$9,$I15+$J15,0) -> 0 | AF15: =IF($C15=AF$9,$I15+$J15,0) -> 0 | AG15: =IF($C15=AG$9,$I15+$J15,0) -> 0 | AI15: =IF($C15=AI$9,$I15+$J15,0) -> 0 | AJ15: =IF($C15=AJ$9,$I15+$J15,0) -> 0 | AK15: =IF($C15=AK$9,$I15+$J15,0) -> 0 | AL15: =IF($C15=AL$9,$I15+$J15,0) -> 0 | AM15: =IF($C15=AM$9,$I15+$J15,0) -> 0 | AN15: =IF($C15=AN$9,$I15+$J15,0) -> 0 | AO15: =IF($C15=AO$9,$I15+$J15,0) -> 0 | AP15: =IF($C15=AP$9,$I15+$J15,0) -> 0 | ... AX15: =IF($C15=AX$9,$I15+$J15,0) -> 0 | AZ15: =IF($C15=AZ$9,$I15+$J15,0) -> 0 | BD15: =IF(B15="","",B15) -> 45836 | BE15: =IF(C15="","",$C$5&"-"&A15) -> HSBC HKD SA-2501-004 | BG15: =IF(BE15="","",COUNTIF(BE:BE,BE15)*2) -> 2 | BH15: =IF(C15="","",IF($C$4="","",VLOOKUP($C$4,'Chart of Accounts'!$A:$B,2,FALSE))) -> 1020 | BI15: =IF(C15="","",VLOOKUP(C:C,'Chart of Accounts'!$A:$B,2,FALSE)) -> 4100 | BJ15: =IF(C15="","",C15&":"&D15&IF(E15="",""," - "&E15)&IF(F15="",""," - "&F15)&IF(G15="",""," - "&TEXT(G15,"MMM-YY"))) -> Bank interest income:CREDIT INTEREST | BK15: =SUM(I15:J15) -> 0.01 | BL15: =-BK15 -> -0.01
A16: 2501-005 | B16: 45840 | C16: Interbank | D16: FROM HESEN (HK) TDG | I16: =23501.4-101.4 -> 23400 | K16: =K14+I16+J16 -> 25727.63 | M16: =SUM(I16:J16)-SUM(N16:BA16) -> 0 | O16: =IF($C16=O$9,$I16+$J16,0) -> 23400 | Q16: =IF($C16=Q$9,$I16+$J16,0) -> 0 | R16: =IF($C16=R$9,$I16+$J16,0) -> 0 | T16: =IF($C16=T$9,$I16+$J16,0) -> 0 | V16: =IF($C16=V$9,$I16+$J16,0) -> 0 | W16: =IF($C16=W$9,$I16+$J16,0) -> 0 | X16: =IF($C16=X$9,$I16+$J16,0) -> 0 | Z16: =IF($C16=Z$9,$I16+$J16,0) -> 0 | AA16: =IF($C16=AA$9,$I16+$J16,0) -> 0 | AC16: =IF($C16=AC$9,$I16+$J16,0) -> 0 | AE16: =IF($C16=AE$9,$I16+$J16,0) -> 0 | AF16: =IF($C16=AF$9,$I16+$J16,0) -> 0 | AG16: =IF($C16=AG$9,$I16+$J16,0) -> 0 | AI16: =IF($C16=AI$9,$I16+$J16,0) -> 0 | AJ16: =IF($C16=AJ$9,$I16+$J16,0) -> 0 | AK16: =IF($C16=AK$9,$I16+$J16,0) -> 0 | AL16: =IF($C16=AL$9,$I16+$J16,0) -> 0 | AM16: =IF($C16=AM$9,$I16+$J16,0) -> 0 | AN16: =IF($C16=AN$9,$I16+$J16,0) -> 0 | AO16: =IF($C16=AO$9,$I16+$J16,0) -> 0 | AP16: =IF($C16=AP$9,$I16+$J16,0) -> 0 | ... AX16: =IF($C16=AX$9,$I16+$J16,0) -> 0 | AZ16: =IF($C16=AZ$9,$I16+$J16,0) -> 0 | BD16: =IF(B16="","",B16) -> 45840 | BE16: =IF(C16="","",$C$5&"-"&A16) -> HSBC HKD SA-2501-005 | BG16: =IF(BE16="","",COUNTIF(BE:BE,BE16)*2) -> 4 | BH16: =IF(C16="","",IF($C$4="","",VLOOKUP($C$4,'Chart of Accounts'!$A:$B,2,FALSE))) -> 1020 | BI16: =IF(C16="","",VLOOKUP(C:C,'Chart of Accounts'!$A:$B,2,FALSE)) -> 1090 | BJ16: =IF(C16="","",C16&":"&D16&IF(E16="",""," - "&E16)&IF(F16="",""," - "&F16)&IF(G16="",""," - "&TEXT(G16,"MMM-YY"))) -> Interbank:FROM HESEN (HK) TDG | BK16: =SUM(I16:J16) -> 23400 | BL16: =-BK16 -> -23400
A17: 2501-005 | B17: 45840 | C17: Exchange losses/(gains), net | D17: FROM HESEN (HK) TDG | I17: =23501.4-23400 -> 101.4 | K17: =K15+I17+J17 -> 2429.04 | M17: =SUM(I17:J17)-SUM(N17:BA17) -> 0 | O17: =IF($C17=O$9,$I17+$J17,0) -> 0 | Q17: =IF($C17=Q$9,$I17+$J17,0) -> 0 | R17: =IF($C17=R$9,$I17+$J17,0) -> 0 | T17: =IF($C17=T$9,$I17+$J17,0) -> 0 | V17: =IF($C17=V$9,$I17+$J17,0) -> 0 | W17: =IF($C17=W$9,$I17+$J17,0) -> 0 | X17: =IF($C17=X$9,$I17+$J17,0) -> 0 | Z17: =IF($C17=Z$9,$I17+$J17,0) -> 0 | AA17: =IF($C17=AA$9,$I17+$J17,0) -> 0 | AC17: =IF($C17=AC$9,$I17+$J17,0) -> 0 | AE17: =IF($C17=AE$9,$I17+$J17,0) -> 0 | AF17: =IF($C17=AF$9,$I17+$J17,0) -> 0 | AG17: =IF($C17=AG$9,$I17+$J17,0) -> 0 | AI17: =IF($C17=AI$9,$I17+$J17,0) -> 0 | AJ17: =IF($C17=AJ$9,$I17+$J17,0) -> 0 | AK17: =IF($C17=AK$9,$I17+$J17,0) -> 0 | AL17: =IF($C17=AL$9,$I17+$J17,0) -> 0 | AM17: =IF($C17=AM$9,$I17+$J17,0) -> 101.4 | AN17: =IF($C17=AN$9,$I17+$J17,0) -> 0 | AO17: =IF($C17=AO$9,$I17+$J17,0) -> 0 | AP17: =IF($C17=AP$9,$I17+$J17,0) -> 0 | ... AX17: =IF($C17=AX$9,$I17+$J17,0) -> 0 | AZ17: =IF($C17=AZ$9,$I17+$J17,0) -> 0 | BD17: =IF(B17="","",B17) -> 45840 | BE17: =IF(C17="","",$C$5&"-"&A17) -> HSBC HKD SA-2501-005 | BG17: =IF(BE17="","",COUNTIF(BE:BE,BE17)*2) -> 4 | BH17: =IF(C17="","",IF($C$4="","",VLOOKUP($C$4,'Chart of Accounts'!$A:$B,2,FALSE))) -> 1020 | BI17: =IF(C17="","",VLOOKUP(C:C,'Chart of Accounts'!$A:$B,2,FALSE)) -> 6580 | BJ17: =IF(C17="","",C17&":"&D17&IF(E17="",""," - "&E17)&IF(F17="",""," - "&F17)&IF(G17="",""," - "&TEXT(G17,"MMM-YY"))) -> Exchange losses/(gains), net:FROM HESEN (HK) TDG | BK17: =SUM(I17:J17) -> 101.4 | BL17: =-BK17 -> -101.4
A18: 2501-006 | B18: 45840 | C18: Director's C/A | D18: ATM WITHDRAWAL | J18: -20000 | K18: =K17+I18+J18 -> -17570.96 | M18: =SUM(I18:J18)-SUM(N18:BA18) -> 0 | O18: =IF($C18=O$9,$I18+$J18,0) -> 0 | Q18: =IF($C18=Q$9,$I18+$J18,0) -> 0 | R18: =IF($C18=R$9,$I18+$J18,0) -> 0 | T18: =IF($C18=T$9,$I18+$J18,0) -> -20000 | V18: =IF($C18=V$9,$I18+$J18,0) -> 0 | W18: =IF($C18=W$9,$I18+$J18,0) -> 0 | X18: =IF($C18=X$9,$I18+$J18,0) -> 0 | Z18: =IF($C18=Z$9,$I18+$J18,0) -> 0 | AA18: =IF($C18=AA$9,$I18+$J18,0) -> 0 | AC18: =IF($C18=AC$9,$I18+$J18,0) -> 0 | AE18: =IF($C18=AE$9,$I18+$J18,0) -> 0 | AF18: =IF($C18=AF$9,$I18+$J18,0) -> 0 | AG18: =IF($C18=AG$9,$I18+$J18,0) -> 0 | AI18: =IF($C18=AI$9,$I18+$J18,0) -> 0 | AJ18: =IF($C18=AJ$9,$I18+$J18,0) -> 0 | AK18: =IF($C18=AK$9,$I18+$J18,0) -> 0 | AL18: =IF($C18=AL$9,$I18+$J18,0) -> 0 | AM18: =IF($C18=AM$9,$I18+$J18,0) -> 0 | AN18: =IF($C18=AN$9,$I18+$J18,0) -> 0 | AO18: =IF($C18=AO$9,$I18+$J18,0) -> 0 | AP18: =IF($C18=AP$9,$I18+$J18,0) -> 0 | ... AX18: =IF($C18=AX$9,$I18+$J18,0) -> 0 | AZ18: =IF($C18=AZ$9,$I18+$J18,0) -> 0 | BD18: =IF(B18="","",B18) -> 45840 | BE18: =IF(C18="","",$C$5&"-"&A18) -> HSBC HKD SA-2501-006 | BG18: =IF(BE18="","",COUNTIF(BE:BE,BE18)*2) -> 2 | BH18: =IF(C18="","",IF($C$4="","",VLOOKUP($C$4,'Chart of Accounts'!$A:$B,2,FALSE))) -> 1020 | BI18: =IF(C18="","",VLOOKUP(C:C,'Chart of Accounts'!$A:$B,2,FALSE)) -> 2400 | BJ18: =IF(C18="","",C18&":"&D18&IF(E18="",""," - "&E18)&IF(F18="",""," - "&F18)&IF(G18="",""," - "&TEXT(G18,"MMM-YY"))) -> Director's C/A:ATM WITHDRAWAL | BK18: =SUM(I18:J18) -> -20000 | BL18: =-BK18 -> 20000
A19: 2501-007 | B19: 45861 | C19: Bank charges | D19: 175-220185-833 | J19: -100 | K19: =K18+I19+J19 -> -17670.96 | M19: =SUM(I19:J19)-SUM(N19:BA19) -> 0 | O19: =IF($C19=O$9,$I19+$J19,0) -> 0 | Q19: =IF($C19=Q$9,$I19+$J19,0) -> 0 | R19: =IF($C19=R$9,$I19+$J19,0) -> 0 | T19: =IF($C19=T$9,$I19+$J19,0) -> 0 | V19: =IF($C19=V$9,$I19+$J19,0) -> 0 | W19: =IF($C19=W$9,$I19+$J19,0) -> 0 | X19: =IF($C19=X$9,$I19+$J19,0) -> 0 | Z19: =IF($C19=Z$9,$I19+$J19,0) -> 0 | AA19: =IF($C19=AA$9,$I19+$J19,0) -> 0 | AC19: =IF($C19=AC$9,$I19+$J19,0) -> 0 | AE19: =IF($C19=AE$9,$I19+$J19,0) -> 0 | AF19: =IF($C19=AF$9,$I19+$J19,0) -> 0 | AG19: =IF($C19=AG$9,$I19+$J19,0) -> 0 | AI19: =IF($C19=AI$9,$I19+$J19,0) -> 0 | AJ19: =IF($C19=AJ$9,$I19+$J19,0) -> -100 | AK19: =IF($C19=AK$9,$I19+$J19,0) -> 0 | AL19: =IF($C19=AL$9,$I19+$J19,0) -> 0 | AM19: =IF($C19=AM$9,$I19+$J19,0) -> 0 | AN19: =IF($C19=AN$9,$I19+$J19,0) -> 0 | AO19: =IF($C19=AO$9,$I19+$J19,0) -> 0 | AP19: =IF($C19=AP$9,$I19+$J19,0) -> 0 | ... AX19: =IF($C19=AX$9,$I19+$J19,0) -> 0 | AZ19: =IF($C19=AZ$9,$I19+$J19,0) -> 0 | BD19: =IF(B19="","",B19) -> 45861 | BE19: =IF(C19="","",$C$5&"-"&A19) -> HSBC HKD SA-2501-007 | BG19: =IF(BE19="","",COUNTIF(BE:BE,BE19)*2) -> 2 | BH19: =IF(C19="","",IF($C$4="","",VLOOKUP($C$4,'Chart of Accounts'!$A:$B,2,FALSE))) -> 1020 | BI19: =IF(C19="","",VLOOKUP(C:C,'Chart of Accounts'!$A:$B,2,FALSE)) -> 6200 | BJ19: =IF(C19="","",C19&":"&D19&IF(E19="",""," - "&E19)&IF(F19="",""," - "&F19)&IF(G19="",""," - "&TEXT(G19,"MMM-YY"))) -> Bank charges:175-220185-833 | BK19: =SUM(I19:J19) -> -100 | BL19: =-BK19 -> 100
A20: 2501-008 | B20: 45866 | C20: Bank interest income | D20: CREDIT INTEREST | I20: 1.21 | K20: =K19+I20+J20 -> -17669.75 | M20: =SUM(I20:J20)-SUM(N20:BA20) -> 0 | O20: =IF($C20=O$9,$I20+$J20,0) -> 0 | Q20: =IF($C20=Q$9,$I20+$J20,0) -> 0 | R20: =IF($C20=R$9,$I20+$J20,0) -> 0 | T20: =IF($C20=T$9,$I20+$J20,0) -> 0 | V20: =IF($C20=V$9,$I20+$J20,0) -> 0 | W20: =IF($C20=W$9,$I20+$J20,0) -> 0 | X20: =IF($C20=X$9,$I20+$J20,0) -> 0 | Z20: =IF($C20=Z$9,$I20+$J20,0) -> 0 | AA20: =IF($C20=AA$9,$I20+$J20,0) -> 0 | AC20: =IF($C20=AC$9,$I20+$J20,0) -> 1.21 | AE20: =IF($C20=AE$9,$I20+$J20,0) -> 0 | AF20: =IF($C20=AF$9,$I20+$J20,0) -> 0 | AG20: =IF($C20=AG$9,$I20+$J20,0) -> 0 | AI20: =IF($C20=AI$9,$I20+$J20,0) -> 0 | AJ20: =IF($C20=AJ$9,$I20+$J20,0) -> 0 | AK20: =IF($C20=AK$9,$I20+$J20,0) -> 0 | AL20: =IF($C20=AL$9,$I20+$J20,0) -> 0 | AM20: =IF($C20=AM$9,$I20+$J20,0) -> 0 | AN20: =IF($C20=AN$9,$I20+$J20,0) -> 0 | AO20: =IF($C20=AO$9,$I20+$J20,0) -> 0 | AP20: =IF($C20=AP$9,$I20+$J20,0) -> 0 | ... AX20: =IF($C20=AX$9,$I20+$J20,0) -> 0 | AZ20: =IF($C20=AZ$9,$I20+$J20,0) -> 0 | BD20: =IF(B20="","",B20) -> 45866 | BE20: =IF(C20="","",$C$5&"-"&A20) -> HSBC HKD SA-2501-008 | BG20: =IF(BE20="","",COUNTIF(BE:BE,BE20)*2) -> 2 | BH20: =IF(C20="","",IF($C$4="","",VLOOKUP($C$4,'Chart of Accounts'!$A:$B,2,FALSE))) -> 1020 | BI20: =IF(C20="","",VLOOKUP(C:C,'Chart of Accounts'!$A:$B,2,FALSE)) -> 4100 | BJ20: =IF(C20="","",C20&":"&D20&IF(E20="",""," - "&E20)&IF(F20="",""," - "&F20)&IF(G20="",""," - "&TEXT(G20,"MMM-YY"))) -> Bank interest income:CREDIT INTEREST | BK20: =SUM(I20:J20) -> 1.21 | BL20: =-BK20 -> -1.21
A21: 2501-009 | B21: 45897 | C21: Bank interest income | D21: CREDIT INTEREST | I21: 1.22 | K21: =K20+I21+J21 -> -17668.53 | M21: =SUM(I21:J21)-SUM(N21:BA21) -> 0 | O21: =IF($C21=O$9,$I21+$J21,0) -> 0 | Q21: =IF($C21=Q$9,$I21+$J21,0) -> 0 | R21: =IF($C21=R$9,$I21+$J21,0) -> 0 | T21: =IF($C21=T$9,$I21+$J21,0) -> 0 | V21: =IF($C21=V$9,$I21+$J21,0) -> 0 | W21: =IF($C21=W$9,$I21+$J21,0) -> 0 | X21: =IF($C21=X$9,$I21+$J21,0) -> 0 | Z21: =IF($C21=Z$9,$I21+$J21,0) -> 0 | AA21: =IF($C21=AA$9,$I21+$J21,0) -> 0 | AC21: =IF($C21=AC$9,$I21+$J21,0) -> 1.22 | AE21: =IF($C21=AE$9,$I21+$J21,0) -> 0 | AF21: =IF($C21=AF$9,$I21+$J21,0) -> 0 | AG21: =IF($C21=AG$9,$I21+$J21,0) -> 0 | AI21: =IF($C21=AI$9,$I21+$J21,0) -> 0 | AJ21: =IF($C21=AJ$9,$I21+$J21,0) -> 0 | AK21: =IF($C21=AK$9,$I21+$J21,0) -> 0 | AL21: =IF($C21=AL$9,$I21+$J21,0) -> 0 | AM21: =IF($C21=AM$9,$I21+$J21,0) -> 0 | AN21: =IF($C21=AN$9,$I21+$J21,0) -> 0 | AO21: =IF($C21=AO$9,$I21+$J21,0) -> 0 | AP21: =IF($C21=AP$9,$I21+$J21,0) -> 0 | ... AX21: =IF($C21=AX$9,$I21+$J21,0) -> 0 | AZ21: =IF($C21=AZ$9,$I21+$J21,0) -> 0 | BD21: =IF(B21="","",B21) -> 45897 | BE21: =IF(C21="","",$C$5&"-"&A21) -> HSBC HKD SA-2501-009 | BG21: =IF(BE21="","",COUNTIF(BE:BE,BE21)*2) -> 2 | BH21: =IF(C21="","",IF($C$4="","",VLOOKUP($C$4,'Chart of Accounts'!$A:$B,2,FALSE))) -> 1020 | BI21: =IF(C21="","",VLOOKUP(C:C,'Chart of Accounts'!$A:$B,2,FALSE)) -> 4100 | BJ21: =IF(C21="","",C21&":"&D21&IF(E21="",""," - "&E21)&IF(F21="",""," - "&F21)&IF(G21="",""," - "&TEXT(G21,"MMM-YY"))) -> Bank interest income:CREDIT INTEREST | BK21: =SUM(I21:J21) -> 1.22 | BL21: =-BK21 -> -1.22
A22: 2501-010 | B22: 45927 | C22: Bank interest income | D22: CREDIT INTEREST | I22: 1.03 | K22: =K21+I22+J22 -> -17667.5 | M22: =SUM(I22:J22)-SUM(N22:BA22) -> 0 | O22: =IF($C22=O$9,$I22+$J22,0) -> 0 | Q22: =IF($C22=Q$9,$I22+$J22,0) -> 0 | R22: =IF($C22=R$9,$I22+$J22,0) -> 0 | T22: =IF($C22=T$9,$I22+$J22,0) -> 0 | V22: =IF($C22=V$9,$I22+$J22,0) -> 0 | W22: =IF($C22=W$9,$I22+$J22,0) -> 0 | X22: =IF($C22=X$9,$I22+$J22,0) -> 0 | Z22: =IF($C22=Z$9,$I22+$J22,0) -> 0 | AA22: =IF($C22=AA$9,$I22+$J22,0) -> 0 | AC22: =IF($C22=AC$9,$I22+$J22,0) -> 1.03 | AE22: =IF($C22=AE$9,$I22+$J22,0) -> 0 | AF22: =IF($C22=AF$9,$I22+$J22,0) -> 0 | AG22: =IF($C22=AG$9,$I22+$J22,0) -> 0 | AI22: =IF($C22=AI$9,$I22+$J22,0) -> 0 | AJ22: =IF($C22=AJ$9,$I22+$J22,0) -> 0 | AK22: =IF($C22=AK$9,$I22+$J22,0) -> 0 | AL22: =IF($C22=AL$9,$I22+$J22,0) -> 0 | AM22: =IF($C22=AM$9,$I22+$J22,0) -> 0 | AN22: =IF($C22=AN$9,$I22+$J22,0) -> 0 | AO22: =IF($C22=AO$9,$I22+$J22,0) -> 0 | AP22: =IF($C22=AP$9,$I22+$J22,0) -> 0 | ... AX22: =IF($C22=AX$9,$I22+$J22,0) -> 0 | AZ22: =IF($C22=AZ$9,$I22+$J22,0) -> 0 | BD22: =IF(B22="","",B22) -> 45927 | BE22: =IF(C22="","",$C$5&"-"&A22) -> HSBC HKD SA-2501-010 | BG22: =IF(BE22="","",COUNTIF(BE:BE,BE22)*2) -> 2 | BH22: =IF(C22="","",IF($C$4="","",VLOOKUP($C$4,'Chart of Accounts'!$A:$B,2,FALSE))) -> 1020 | BI22: =IF(C22="","",VLOOKUP(C:C,'Chart of Accounts'!$A:$B,2,FALSE)) -> 4100 | BJ22: =IF(C22="","",C22&":"&D22&IF(E22="",""," - "&E22)&IF(F22="",""," - "&F22)&IF(G22="",""," - "&TEXT(G22,"MMM-YY"))) -> Bank interest income:CREDIT INTEREST | BK22: =SUM(I22:J22) -> 1.03 | BL22: =-BK22 -> -1.03
A23: 2501-011 | B23: 45957 | C23: Director's C/A | D23: ATM WITHDRAWAL | J23: -5000 | K23: =K22+I23+J23 -> -22667.5 | M23: =SUM(I23:J23)-SUM(N23:BA23) -> 0 | O23: =IF($C23=O$9,$I23+$J23,0) -> 0 | Q23: =IF($C23=Q$9,$I23+$J23,0) -> 0 | R23: =IF($C23=R$9,$I23+$J23,0) -> 0 | T23: =IF($C23=T$9,$I23+$J23,0) -> -5000 | V23: =IF($C23=V$9,$I23+$J23,0) -> 0 | W23: =IF($C23=W$9,$I23+$J23,0) -> 0 | X23: =IF($C23=X$9,$I23+$J23,0) -> 0 | Z23: =IF($C23=Z$9,$I23+$J23,0) -> 0 | AA23: =IF($C23=AA$9,$I23+$J23,0) -> 0 | AC23: =IF($C23=AC$9,$I23+$J23,0) -> 0 | AE23: =IF($C23=AE$9,$I23+$J23,0) -> 0 | AF23: =IF($C23=AF$9,$I23+$J23,0) -> 0 | AG23: =IF($C23=AG$9,$I23+$J23,0) -> 0 | AI23: =IF($C23=AI$9,$I23+$J23,0) -> 0 | AJ23: =IF($C23=AJ$9,$I23+$J23,0) -> 0 | AK23: =IF($C23=AK$9,$I23+$J23,0) -> 0 | AL23: =IF($C23=AL$9,$I23+$J23,0) -> 0 | AM23: =IF($C23=AM$9,$I23+$J23,0) -> 0 | AN23: =IF($C23=AN$9,$I23+$J23,0) -> 0 | AO23: =IF($C23=AO$9,$I23+$J23,0) -> 0 | AP23: =IF($C23=AP$9,$I23+$J23,0) -> 0 | ... AX23: =IF($C23=AX$9,$I23+$J23,0) -> 0 | AZ23: =IF($C23=AZ$9,$I23+$J23,0) -> 0 | BD23: =IF(B23="","",B23) -> 45957 | BE23: =IF(C23="","",$C$5&"-"&A23) -> HSBC HKD SA-2501-011 | BG23: =IF(BE23="","",COUNTIF(BE:BE,BE23)*2) -> 2 | BH23: =IF(C23="","",IF($C$4="","",VLOOKUP($C$4,'Chart of Accounts'!$A:$B,2,FALSE))) -> 1020 | BI23: =IF(C23="","",VLOOKUP(C:C,'Chart of Accounts'!$A:$B,2,FALSE)) -> 2400 | BJ23: =IF(C23="","",C23&":"&D23&IF(E23="",""," - "&E23)&IF(F23="",""," - "&F23)&IF(G23="",""," - "&TEXT(G23,"MMM-YY"))) -> Director's C/A:ATM WITHDRAWAL | BK23: =SUM(I23:J23) -> -5000 | BL23: =-BK23 -> 5000
A24: 2501-012 | B24: 45958 | C24: Bank interest income | D24: CREDIT INTEREST | I24: 0.59 | K24: =K23+I24+J24 -> -22666.91 | M24: =SUM(I24:J24)-SUM(N24:BA24) -> 0 | O24: =IF($C24=O$9,$I24+$J24,0) -> 0 | Q24: =IF($C24=Q$9,$I24+$J24,0) -> 0 | R24: =IF($C24=R$9,$I24+$J24,0) -> 0 | T24: =IF($C24=T$9,$I24+$J24,0) -> 0 | V24: =IF($C24=V$9,$I24+$J24,0) -> 0 | W24: =IF($C24=W$9,$I24+$J24,0) -> 0 | X24: =IF($C24=X$9,$I24+$J24,0) -> 0 | Z24: =IF($C24=Z$9,$I24+$J24,0) -> 0 | AA24: =IF($C24=AA$9,$I24+$J24,0) -> 0 | AC24: =IF($C24=AC$9,$I24+$J24,0) -> 0.59 | AE24: =IF($C24=AE$9,$I24+$J24,0) -> 0 | AF24: =IF($C24=AF$9,$I24+$J24,0) -> 0 | AG24: =IF($C24=AG$9,$I24+$J24,0) -> 0 | AI24: =IF($C24=AI$9,$I24+$J24,0) -> 0 | AJ24: =IF($C24=AJ$9,$I24+$J24,0) -> 0 | AK24: =IF($C24=AK$9,$I24+$J24,0) -> 0 | AL24: =IF($C24=AL$9,$I24+$J24,0) -> 0 | AM24: =IF($C24=AM$9,$I24+$J24,0) -> 0 | AN24: =IF($C24=AN$9,$I24+$J24,0) -> 0 | AO24: =IF($C24=AO$9,$I24+$J24,0) -> 0 | AP24: =IF($C24=AP$9,$I24+$J24,0) -> 0 | ... AX24: =IF($C24=AX$9,$I24+$J24,0) -> 0 | AZ24: =IF($C24=AZ$9,$I24+$J24,0) -> 0 | BD24: =IF(B24="","",B24) -> 45958 | BE24: =IF(C24="","",$C$5&"-"&A24) -> HSBC HKD SA-2501-012 | BG24: =IF(BE24="","",COUNTIF(BE:BE,BE24)*2) -> 2 | BH24: =IF(C24="","",IF($C$4="","",VLOOKUP($C$4,'Chart of Accounts'!$A:$B,2,FALSE))) -> 1020 | BI24: =IF(C24="","",VLOOKUP(C:C,'Chart of Accounts'!$A:$B,2,FALSE)) -> 4100 | BJ24: =IF(C24="","",C24&":"&D24&IF(E24="",""," - "&E24)&IF(F24="",""," - "&F24)&IF(G24="",""," - "&TEXT(G24,"MMM-YY"))) -> Bank interest income:CREDIT INTEREST | BK24: =SUM(I24:J24) -> 0.59 | BL24: =-BK24 -> -0.59
A25: 2502-001 | B25: 45992 | C25: Bank charges | D25: ACCT MAINT FEE | J25: -150 | K25: =K24+I25+J25 -> -22816.91 | M25: =SUM(I25:J25)-SUM(N25:BA25) -> 0 | O25: =IF($C25=O$9,$I25+$J25,0) -> 0 | Q25: =IF($C25=Q$9,$I25+$J25,0) -> 0 | R25: =IF($C25=R$9,$I25+$J25,0) -> 0 | T25: =IF($C25=T$9,$I25+$J25,0) -> 0 | V25: =IF($C25=V$9,$I25+$J25,0) -> 0 | W25: =IF($C25=W$9,$I25+$J25,0) -> 0 | X25: =IF($C25=X$9,$I25+$J25,0) -> 0 | Z25: =IF($C25=Z$9,$I25+$J25,0) -> 0 | AA25: =IF($C25=AA$9,$I25+$J25,0) -> 0 | AC25: =IF($C25=AC$9,$I25+$J25,0) -> 0 | AE25: =IF($C25=AE$9,$I25+$J25,0) -> 0 | AF25: =IF($C25=AF$9,$I25+$J25,0) -> 0 | AG25: =IF($C25=AG$9,$I25+$J25,0) -> 0 | AI25: =IF($C25=AI$9,$I25+$J25,0) -> 0 | AJ25: =IF($C25=AJ$9,$I25+$J25,0) -> -150 | AK25: =IF($C25=AK$9,$I25+$J25,0) -> 0 | AL25: =IF($C25=AL$9,$I25+$J25,0) -> 0 | AM25: =IF($C25=AM$9,$I25+$J25,0) -> 0 | AN25: =IF($C25=AN$9,$I25+$J25,0) -> 0 | AO25: =IF($C25=AO$9,$I25+$J25,0) -> 0 | AP25: =IF($C25=AP$9,$I25+$J25,0) -> 0 | ... AX25: =IF($C25=AX$9,$I25+$J25,0) -> 0 | AZ25: =IF($C25=AZ$9,$I25+$J25,0) -> 0 | BD25: =IF(B25="","",B25) -> 45992 | BE25: =IF(C25="","",$C$5&"-"&A25) -> HSBC HKD SA-2502-001 | BG25: =IF(BE25="","",COUNTIF(BE:BE,BE25)*2) -> 2 | BH25: =IF(C25="","",IF($C$4="","",VLOOKUP($C$4,'Chart of Accounts'!$A:$B,2,FALSE))) -> 1020 | BI25: =IF(C25="","",VLOOKUP(C:C,'Chart of Accounts'!$A:$B,2,FALSE)) -> 6200 | BJ25: =IF(C25="","",C25&":"&D25&IF(E25="",""," - "&E25)&IF(F25="",""," - "&F25)&IF(G25="",""," - "&TEXT(G25,"MMM-YY"))) -> Bank charges:ACCT MAINT FEE | BK25: =SUM(I25:J25) -> -150 | BL25: =-BK25 -> 150
I27: =SUBTOTAL(9,I11:I26) -> 23505.47 | J27: =SUBTOTAL(9,J11:J26) -> -26160 | M27: =SUM(I27:J27)-SUM(N27:AY27) -> 0 | O27: =SUBTOTAL(9,O11:O26) -> 23400 | Q27: =SUBTOTAL(9,Q11:Q26) -> 0 | R27: =SUBTOTAL(9,R11:R26) -> 0 | T27: =SUBTOTAL(9,T11:T26) -> -25000 | V27: =SUBTOTAL(9,V11:V26) -> 0 | W27: =SUBTOTAL(9,W11:W26) -> 0 | X27: =SUBTOTAL(9,X11:X26) -> 0 | Z27: =SUBTOTAL(9,Z11:Z26) -> 0 | AA27: =SUBTOTAL(9,AA11:AA26) -> 0 | AC27: =SUBTOTAL(9,AC11:AC26) -> 4.07 | AE27: =SUBTOTAL(9,AE11:AE26) -> 0 | AF27: =SUBTOTAL(9,AF11:AF26) -> 0 | AG27: =SUBTOTAL(9,AG11:AG26) -> 0 | AI27: =SUBTOTAL(9,AI11:AI26) -> 0 | AJ27: =SUBTOTAL(9,AJ11:AJ26) -> -1160 | AK27: =SUBTOTAL(9,AK11:AK26) -> 0 | AL27: =SUBTOTAL(9,AL11:AL26) -> 0 | AM27: =SUBTOTAL(9,AM11:AM26) -> 101.4 | AN27: =SUBTOTAL(9,AN11:AN26) -> 0 | AO27: =SUBTOTAL(9,AO11:AO26) -> 0 | AP27: =SUBTOTAL(9,AP11:AP26) -> 0 | ... AX27: =SUBTOTAL(9,AX11:AX26) -> 0 | AZ27: =SUBTOTAL(9,AZ11:AZ26) -> 0 | BK27: =SUBTOTAL(9,BK11:BK26) -> -2654.53 | BL27: =SUBTOTAL(9,BL11:BL26) -> 2654.53
BL28: =SUM(BK27:BL27) -> 0

Sheet HSBC USD SA
A1: Company Name | C1: Hesen (Hong Kong) Trading Limited | J1: Remind | K1: - "+ve" for income, "-ve" for expenses
A2: Period | C2: 1.1.25-31.12.25 | K2: - 1 file for each bank account
A3: Bank record | C3: HSBC USD S/A #121-891824-838
A4: Bank COA: | C4: HSBC USD SA
A5: Bank name: | C5: HSBC USD SA
M8: Ex-rate | N8: 7.8 | Y8: For Peachtree import use - Please don't move this column
A9: No. | B9: Date | C9: Particular | I9: Deposit | J9: Withdrawal | K9: Balance | M9: Deposit | N9: Withdrawal | O9: Balance | Q9: Control | S9: Interbank | U9: Sales | W9: Bank interest income | Y9: Date | Z9: Reference | AB9: Number of Distributions | AC9: G/L Account (Bank) | AD9: G/L Account (Nature) | AE9: Description | AF9: Bank (Amount$) | AG9: Nature (Amount$)
A10: No. | B10: Date | C10: Nature | D10: Payer / (Payee) | E10: Invoice no. (Cheque no.) | F10: Details | G10: Month-Year | I10: USD | J10: USD | K10: USD | M10: HKD | N10: HKD | O10: HKD
A11: 0 | B11: 45658 | C11: Bank opening | K11: 5878.19 | O11: =ROUND(K11*$N$8,2) -> 45849.88
A12: 2501-001 | B12: 45836 | C12: Bank interest income | D12: CREDIT INTEREST | I12: 11.14 | K12: =K11+I12+J12 -> 5889.33 | M12: =ROUND(I12*$N$8,2) -> 86.89 | N12: =ROUND(J12*$N$8,2) -> 0 | O12: =O11+M12+N12 -> 45936.77 | Q12: =SUM(M12:N12)-SUM(R12:W12) -> 0 | S12: =IF($C12=S$9,$M12+$N12,0) -> 0 | U12: =IF($C12=U$9,$M12+$N12,0) -> 0 | W12: =IF($C12=W$9,$M12+$N12,0) -> 86.89 | Y12: =IF(B12="","",B12) -> 45836 | Z12: =IF(C12="","",$C$5&"-"&A12) -> HSBC USD SA-2501-001 | AB12: =IF(Z12="","",COUNTIF(Z:Z,Z12)*2) -> 2 | AC12: =IF(C12="","",IF($C$4="","",VLOOKUP($C$4,'Chart of Accounts'!$A:$B,2,FALSE))) -> 1010 | AD12: =IF(C12="","",VLOOKUP(C:C,'Chart of Accounts'!$A:$B,2,FALSE)) -> 4100 | AE12: =IF(C12="","",D12&":"&E12&IF(E12="",""," - "&E12)&IF(F12="",""," - "&F12)&IF(G12="",""," - "&TEXT(G12,"MMM-YY"))) -> CREDIT INTEREST: | AF12: =SUM(M12:N12) -> 86.89 | AG12: =-AF12 -> -86.89
A13: 2501-002 | B13: 45840 | C13: Interbank | D13: 121-891824-838 | J13: -3000 | K13: =K12+I13+J13 -> 2889.33 | M13: =ROUND(I13*$N$8,2) -> 0 | N13: =ROUND(J13*$N$8,2) -> -23400 | O13: =O12+M13+N13 -> 22536.77 | Q13: =SUM(M13:N13)-SUM(R13:W13) -> 0 | S13: =IF($C13=S$9,$M13+$N13,0) -> -23400 | U13: =IF($C13=U$9,$M13+$N13,0) -> 0 | W13: =IF($C13=W$9,$M13+$N13,0) -> 0 | Y13: =IF(B13="","",B13) -> 45840 | Z13: =IF(C13="","",$C$5&"-"&A13) -> HSBC USD SA-2501-002 | AB13: =IF(Z13="","",COUNTIF(Z:Z,Z13)*2) -> 2 | AC13: =IF(C13="","",IF($C$4="","",VLOOKUP($C$4,'Chart of Accounts'!$A:$B,2,FALSE))) -> 1010 | AD13: =IF(C13="","",VLOOKUP(C:C,'Chart of Accounts'!$A:$B,2,FALSE)) -> 1090 | AE13: =IF(C13="","",D13&":"&E13&IF(E13="",""," - "&E13)&IF(F13="",""," - "&F13)&IF(G13="",""," - "&TEXT(G13,"MMM-YY"))) -> 121-891824-838: | AF13: =SUM(M13:N13) -> -23400 | AG13: =-AF13 -> 23400
A14: 2501-003 | B14: 45877 | C14: Sales | D14: DEPOSIT | I14: 8247.59 | K14: =K13+I14+J14 -> 11136.92 | M14: =ROUND(I14*$N$8,2) -> 64331.2 | N14: =ROUND(J14*$N$8,2) -> 0 | O14: =O13+M14+N14 -> 86867.97 | Q14: =SUM(M14:N14)-SUM(R14:W14) -> 0 | S14: =IF($C14=S$9,$M14+$N14,0) -> 0 | U14: =IF($C14=U$9,$M14+$N14,0) -> 64331.2 | W14: =IF($C14=W$9,$M14+$N14,0) -> 0 | Y14: =IF(B14="","",B14) -> 45877 | Z14: =IF(C14="","",$C$5&"-"&A14) -> HSBC USD SA-2501-003 | AB14: =IF(Z14="","",COUNTIF(Z:Z,Z14)*2) -> 2 | AC14: =IF(C14="","",IF($C$4="","",VLOOKUP($C$4,'Chart of Accounts'!$A:$B,2,FALSE))) -> 1010 | AD14: =IF(C14="","",VLOOKUP(C:C,'Chart of Accounts'!$A:$B,2,FALSE)) -> 4000 | AE14: =IF(C14="","",D14&":"&E14&IF(E14="",""," - "&E14)&IF(F14="",""," - "&F14)&IF(G14="",""," - "&TEXT(G14,"MMM-YY"))) -> DEPOSIT: | AF14: =SUM(M14:N14) -> 64331.2 | AG14: =-AF14 -> -64331.2
A15: 2501-004 | B15: 46022 | C15: Bank interest income | D15: CREDIT INTEREST | I15: 11.08 | K15: =K14+I15+J15 -> 11148 | M15: =ROUND(I15*$N$8,2) -> 86.42 | N15: =ROUND(J15*$N$8,2) -> 0 | O15: =O14+M15+N15 -> 86954.39 | Q15: =SUM(M15:N15)-SUM(R15:W15) -> 0 | S15: =IF($C15=S$9,$M15+$N15,0) -> 0 | U15: =IF($C15=U$9,$M15+$N15,0) -> 0 | W15: =IF($C15=W$9,$M15+$N15,0) -> 86.42 | Y15: =IF(B15="","",B15) -> 46022 | Z15: =IF(C15="","",$C$5&"-"&A15) -> HSBC USD SA-2501-004 | AB15: =IF(Z15="","",COUNTIF(Z:Z,Z15)*2) -> 2 | AC15: =IF(C15="","",IF($C$4="","",VLOOKUP($C$4,'Chart of Accounts'!$A:$B,2,FALSE))) -> 1010 | AD15: =IF(C15="","",VLOOKUP(C:C,'Chart of Accounts'!$A:$B,2,FALSE)) -> 4100 | AE15: =IF(C15="","",D15&":"&E15&IF(E15="",""," - "&E15)&IF(F15="",""," - "&F15)&IF(G15="",""," - "&TEXT(G15,"MMM-YY"))) -> CREDIT INTEREST: | AF15: =SUM(M15:N15) -> 86.42 | AG15: =-AF15 -> -86.42
A16: 2501-005 | K16: =K15+I16+J16 -> 11148 | M16: =ROUND(I16*$N$8,2) -> 0 | N16: =ROUND(J16*$N$8,2) -> 0 | O16: =O15+M16+N16 -> 86954.39 | Q16: =SUM(M16:N16)-SUM(R16:W16) -> 0 | S16: =IF($C16=S$9,$M16+$N16,0) -> 0 | U16: =IF($C16=U$9,$M16+$N16,0) -> 0 | W16: =IF($C16=W$9,$M16+$N16,0) -> 0 | Y16: =IF(B16="","",B16) | Z16: =IF(C16="","",$C$5&"-"&A16) | AB16: =IF(Z16="","",COUNTIF(Z:Z,Z16)*2) | AC16: =IF(C16="","",IF($C$4="","",VLOOKUP($C$4,'Chart of Accounts'!$A:$B,2,FALSE))) | AD16: =IF(C16="","",VLOOKUP(C:C,'Chart of Accounts'!$A:$B,2,FALSE)) | AE16: =IF(C16="","",D16&":"&E16&IF(E16="",""," - "&E16)&IF(F16="",""," - "&F16)&IF(G16="",""," - "&TEXT(G16,"MMM-YY"))) | AF16: =SUM(M16:N16) -> 0 | AG16: =-AF16 -> 0
I18: =SUBTOTAL(9,I11:I17) -> 8269.81 | J18: =SUBTOTAL(9,J11:J17) -> -3000 | M18: =SUBTOTAL(9,M11:M17) -> 64504.51 | N18: =SUBTOTAL(9,N11:N17) -> -23400 | Q18: =SUM(M18:N18)-SUM(R18:W18) -> 0 | S18: =SUBTOTAL(9,S11:S17) -> -23400 | U18: =SUBTOTAL(9,U11:U17) -> 64331.2 | W18: =SUBTOTAL(9,W11:W17) -> 173.31 | AF18: =SUBTOTAL(9,AF11:AF17) -> 41104.51 | AG18: =SUBTOTAL(9,AG11:AG17) -> -41104.51
AG19: =SUM(AF18:AG18) -> 0

Sheet Chart of Accounts
A1: Account Description | B1: Account ID
A2: Cash | B2: 1000
A3: HSBC USD SA | B3: 1010
A4: HSBC HKD SA | B4: 1020
A5: HSBC HKD CA | B5: 1030
A6: BOC HKD SA | B6: 1040
A7: HSBC HKD Credit Card | B7: 1080
A8: Interbank | B8: 1090
A9: Trade receivable | B9: 1100
A10: Other receivables | B10: 1120
A11: Trade deposit paid | B11: 1150
A12: Rental & utilities deposit | B12: 1200
A13: Prepayment | B13: 1300
... A107: Income tax expenses | B107: 9000
