Workbook

Sheet Master Pg
A1: Client Name: | B1: Pro-surgio Company Limited
A2: Y.E. | B2: 1.4.25-31.3.26
A3: File No.: | B3: P003
A5: Expressed in: | B5: HK$
A7: Acc period from | B7: 45748
A8: Acc period to | B8: 46112
A9: Incorporation / Cessation | C9: DOI / DOC
A11: Job-in-chg:

Sheet Trade Receivables
A1: Name: | B1: ='Master Pg'!$B1 -> Pro-surgio Company Limited
A2: Y.E.: | B2: ='Master Pg'!$B2 -> 1.4.25-31.3.26
A3: File No: | B3: ='Master Pg'!$B3 -> P003
A4: Sec.: | B4: Trade receivable
A5: Expressed in: | B5: ='Master Pg'!$B$5 -> HK$ | W5: For Peachtree import use - Please don't move this column
K6: 1st s/s | O6: 2nd s/s | W6: Date | X6: Reference | Z6: Number of Distributions | AA6: G/L Account (AR) | AB6: G/L Account (Nature) | AC6: Description | AD6: AR (Amount$) | AE6: Nature (Amount$)
A7: No. | B7: Ref. no. | C7: Date | D7: Nature | E7: Customer | F7: Invoices no. | G7: Details | I7: Amount | K7: Bank | L7: Date | M7: Amount | O7: Bank | P7: Date | Q7: Amount | S7: o/s bal. | AA7: Dr. | AB7: Cr. | AD7: Dr. | AE7: Cr.
A8: 1 | B8: 2603-001 | C8: 46112 | D8: Sales | E8: ST TERESA'S HOSPITAL | G8: Sales -16.3.26-31.3.26 | I8: 119600 | K8: HSBC HKD SA | L8: 46114 | M8: 117087 | U8: 119600=117087+2513（Handling Charge) | W8: =IF(C8="","",C8) -> 46112 | X8: =IF(D8="","","AR"&"-"&B8) -> AR-2603-001 | Z8: =IF(X8="","",COUNTIF(X:X,X8)*2) -> 2 | AA8: =IF($D8="","",IF($B$4="","",VLOOKUP($B$4,'Chart of Accounts'!$A:$B,2,FALSE))) -> 1100 | AB8: =IF(D8="","",VLOOKUP(D:D,'Chart of Accounts'!$A:$B,2,FALSE)) -> 4000 | AC8: =IF(D8="","",D8&":"&E8&IF(F8="",""," - "&F8)&IF(G8="",""," - "&G8)) -> Sales:ST TERESA'S HOSPITAL - Sales -16.3.26-31.3.26 | AD8: =I:I -> 119600 | AE8: =-I:I -> -119600
I9: =SUM(I8:I8) -> 119600 | M9: =SUM(M8:M8) -> 117087 | Q9: =SUM(Q8:Q8) -> 0 | S9: =SUM(S8:S8) -> 0 | AD9: =SUM(AD8:AD8) -> 119600 | AE9: =SUM(AE8:AE8) -> -119600
Q10: ^ | S10: ^ | AE10: =SUM(AD9:AE9) -> 0

Sheet Trade payables
A1: Name: | B1: ='Master Pg'!$B1 -> Pro-surgio Company Limited
A2: Y.E.: | B2: ='Master Pg'!$B2 -> 1.4.25-31.3.26
A3: File No: | B3: ='Master Pg'!$B3 -> P003
A4: Sec.: | B4: Trade payable
A5: Expressed in: | B5: ='Master Pg'!$B$5 -> HK$ | W5: For Peachtree import use - Please don't move this column
K6: 1st s/s | O6: 2nd s/s | W6: Date | X6: Reference | Z6: Number of Distributions | AA6: G/L Account (Nature) | AB6: G/L Account (AP) | AC6: Description | AD6: Nature (Amount$) | AE6: AP (Amount$)
A7: No. | B7: Ref. no. | C7: Date | D7: Nature | E7: Customer | F7: Invoices no. | G7: Details | I7: Amount | K7: Bank | L7: Date | M7: Amount | O7: Bank | P7: Date | Q7: Amount | S7: o/s bal. | AA7: Dr. | AB7: Cr. | AD7: Dr. | AE7: Cr.
B8: 2603-001 | C8: 46112 | D8: Handling Charges | E8: ST TERESA'S HOSPITAL | G8: Sales Handling Charges-16.3.26-31.3.26 | I8: 2513 | K8: HSBC HKD SA | L8: 46114 | M8: 2513 | U8: 119600=117087+2513（Handling Charge) | W8: =IF(C8="","",C8) -> 46112 | X8: =IF(D8="","","AP"&"-"&B8) -> AP-2603-001 | Z8: =IF(X8="","",COUNTIF(X:X,X8)*2) -> 2 | AA8: =IF(D8="","",VLOOKUP(D:D,'Chart of Accounts'!$A:$B,2,FALSE)) -> 5300 | AB8: =IF($D8="","",IF($B$4="","",VLOOKUP($B$4,'Chart of Accounts'!$A:$B,2,FALSE))) -> 2000 | AC8: =IF(D8="","",D8&":"&E8&IF(F8="",""," - "&F8)&IF(G8="",""," - "&G8)) -> Handling Charges:ST TERESA'S HOSPITAL - Sales Handling Charges-16.3.26-31.3.26 | AD8: =I:I -> 2513 | AE8: =-I:I -> -2513
W9: =IF(C9="","",C9) | X9: =IF(D9="","","AP"&"-"&B9) | Z9: =IF(X9="","",COUNTIF(X:X,X9)*2) | AA9: =IF(D9="","",VLOOKUP(D:D,'Chart of Accounts'!$A:$B,2,FALSE)) | AB9: =IF($D9="","",IF($B$4="","",VLOOKUP($B$4,'Chart of Accounts'!$A:$B,2,FALSE))) | AC9: =IF(D9="","",D9&":"&E9&IF(F9="",""," - "&F9)&IF(G9="",""," - "&G9)) | AD9: =I:I -> 0 | AE9: =-I:I -> 0
W10: =IF(C10="","",C10) | X10: =IF(D10="","","AP"&"-"&B10) | Z10: =IF(X10="","",COUNTIF(X:X,X10)*2) | AA10: =IF(D10="","",VLOOKUP(D:D,'Chart of Accounts'!$A:$B,2,FALSE)) | AB10: =IF($D10="","",IF($B$4="","",VLOOKUP($B$4,'Chart of Accounts'!$A:$B,2,FALSE))) | AC10: =IF(D10="","",D10&":"&E10&IF(F10="",""," - "&F10)&IF(G10="",""," - "&G10)) | AD10: =I:I -> 0 | AE10: =-I:I -> 0
H12: per TB | I12: =SUM(I8:I11) -> 2513 | M12: =SUM(M8:M11) -> 2513 | Q12: =SUM(Q8:Q11) -> 0 | S12: =SUM(S8:S11) -> 0 | AD12: =SUM(AD8:AD11) -> 2513 | AE12: =SUM(AE8:AE11) -> -2513
I13: ^ | M13: ^ | Q13: ^ | S13: ^ | AE13: =SUM(AD12:AE12) -> 0

Sheet Accruals
A1: Name: | B1: ='Master Pg'!$B1 -> Pro-surgio Company Limited
A2: Y.E.: | B2: ='Master Pg'!$B2 -> 1.4.25-31.3.26
A3: File No: | B3: ='Master Pg'!$B3 -> P003
A4: Sec.: | B4: Accruals
A5: Expressed in: | B5: ='Master Pg'!$B$5 -> HK$ | W5: For Peachtree import use - Please don't move this column
K6: 1st s/s | O6: 2nd s/s | W6: Date | X6: Reference | Z6: Number of Distributions | AA6: G/L Account (Nature) | AB6: G/L Account (Accruals) | AC6: Description | AD6: Nature (Amount$) | AE6: Accruals (Amount$)
A7: No. | B7: Ref. no. | C7: Date | D7: Nature | E7: Customer | F7: Invoices no. | G7: Details | I7: Amount | K7: Bank | L7: Date | M7: Amount | O7: Bank | P7: Date | Q7: Amount | S7: o/s bal. | AA7: Dr. | AB7: Cr. | AD7: Dr. | AE7: Cr.
A8: 1 | B8: 2603-001 | C8: 46112 | D8: Accounting fee | E8: DM Secretary Limited | I8: 8000 | W8: =IF(C8="","",C8) -> 46112 | X8: =IF(D8="","","JV"&"-"&B8) -> JV-2603-001 | Z8: =IF(X8="","",COUNTIF(X:X,X8)*2) -> 6 | AA8: =IF(D8="","",VLOOKUP(D:D,'Chart of Accounts'!$A:$B,2,FALSE)) -> 6000 | AB8: =IF($D8="","",IF($B$4="","",VLOOKUP($B$4,'Chart of Accounts'!$A:$B,2,FALSE))) -> 2200 | AC8: =IF(D8="","",D8&":"&E8&IF(F8="",""," - "&F8)&IF(G8="",""," - "&G8)) -> Accounting fee:DM Secretary Limited | AD8: =I:I -> 8000 | AE8: =-I:I -> -8000
A9: 2 | B9: 2603-001 | C9: 46112 | D9: Auditor's remuneration | E9: Dennis MAK CPA Limited | I9: 10200 | W9: =IF(C9="","",C9) -> 46112 | X9: =IF(D9="","","JV"&"-"&B9) -> JV-2603-001 | Z9: =IF(X9="","",COUNTIF(X:X,X9)*2) -> 6 | AA9: =IF(D9="","",VLOOKUP(D:D,'Chart of Accounts'!$A:$B,2,FALSE)) -> 6100 | AB9: =IF($D9="","",IF($B$4="","",VLOOKUP($B$4,'Chart of Accounts'!$A:$B,2,FALSE))) -> 2200 | AC9: =IF(D9="","",D9&":"&E9&IF(F9="",""," - "&F9)&IF(G9="",""," - "&G9)) -> Auditor's remuneration:Dennis MAK CPA Limited | AD9: =I:I -> 10200 | AE9: =-I:I -> -10200
A10: 3 | B10: 2603-001 | C10: 46112 | D10: Director's remuneration | I10: 700000 | S10: =I:I-M:M-Q:Q -> 700000 | W10: =IF(C10="","",C10) -> 46112 | X10: =IF(D10="","","JV"&"-"&B10) -> JV-2603-001 | Z10: =IF(X10="","",COUNTIF(X:X,X10)*2) -> 6 | AA10: =IF(D10="","",VLOOKUP(D:D,'Chart of Accounts'!$A:$B,2,FALSE)) -> 6450 | AB10: =IF($D10="","",IF($B$4="","",VLOOKUP($B$4,'Chart of Accounts'!$A:$B,2,FALSE))) -> 2200 | AC10: =IF(D10="","",D10&":"&E10&IF(F10="",""," - "&F10)&IF(G10="",""," - "&G10)) -> Director's remuneration: | AD10: =I:I -> 700000 | AE10: =-I:I -> -700000
H12: per TB | I12: =SUM(I8:I11) -> 718200 | M12: =SUM(M8:M11) -> 0 | Q12: =SUM(Q8:Q11) -> 0 | S12: =SUM(S8:S11) -> 700000 | AD12: =SUM(AD8:AD11) -> 718200 | AE12: =SUM(AE8:AE11) -> -718200
I13: ^ | M13: ^ | Q13: ^ | S13: ^ | AE13: =SUM(AD12:AE12) -> 0

Sheet Salaries & MPF
A1: Name: | B1: ='Master Pg'!$B1 -> Pro-surgio Company Limited
A2: Y.E.: | B2: ='Master Pg'!$B2 -> 1.4.25-31.3.26
A3: File No: | B3: ='Master Pg'!$B3 -> P003
A4: Sec.: | B4: Salaries & MPF
A5: Expressed in: | B5: ='Master Pg'!$B$5 -> HK$
A8: Gross salaries
A9: No. | B9: Staff Name | C9: Remarks | D9: Total | E9: 45017 | F9: 45047 | G9: 45078 | H9: 45108 | I9: 45139 | J9: 45170 | K9: 45200 | L9: 45231 | M9: 45261 | N9: 45292 | O9: 45323 | P9: 45352 | Q9: Bonus
A10: 1 | B10: Wan Kar Hing | C10: Director | D10: =SUM(E10:Q10) -> 600000 | E10: 50000 | F10: 50000 | G10: 50000 | H10: 50000 | I10: 50000 | J10: 50000 | K10: 50000 | L10: 50000 | M10: 50000 | N10: 50000 | O10: 50000 | P10: 50000 | Q10: 0
D12: =SUM(D10:D11) -> 600000 | E12: =SUM(E10:E11) -> 50000 | F12: =SUM(F10:F11) -> 50000 | G12: =SUM(G10:G11) -> 50000 | H12: =SUM(H10:H11) -> 50000 | I12: =SUM(I10:I11) -> 50000 | J12: =SUM(J10:J11) -> 50000 | K12: =SUM(K10:K11) -> 50000 | ... Q12: =SUM(Q10:Q11) -> 0
D13: ^, per TB | E13: ^ | F13: ^ | G13: ^ | H13: ^ | I13: ^ | J13: ^ | K13: ^ | L13: ^ | M13: ^ | N13: ^ | O13: ^ | P13: ^ | Q13: ^
A15: 2 | B15: Chiu Yin Ning | C15: Full-time | D15: =SUM(E15:Q15) -> 229488 | E15: 18700 | F15: 18700 | G15: 18700 | H15: 18700 | I15: 18700 | J15: 18700 | K15: 18700 | L15: 18700 | M15: 18700 | N15: 18700 | O15: 18700 | P15: 18700 | Q15: 5088
A16: 3 | B16: Cheung Ka Yee | C16: Full-time | D16: =SUM(E16:Q16) -> 244568 | E16: 19200 | F16: 20080 | G16: 20080 | H16: 20080 | I16: 20080 | J16: 20080 | K16: 20080 | L16: 20080 | M16: 20080 | N16: 20080 | O16: 20080 | P16: 20080 | Q16: 4488
A17: 4 | B17: Chiu Ting Chi | C17: Full-time | D17: =SUM(E17:Q17) -> 306828 | E17: 24315 | F17: 25195 | G17: 25195 | H17: 25195 | I17: 25195 | J17: 25195 | K17: 25195 | L17: 25195 | M17: 25195 | N17: 25195 | O17: 25195 | P17: 25195 | Q17: 5368
A18: 5 | B18: Leung Chung Yi | C18: Full-time | D18: =SUM(E18:Q18) -> 291176 | E18: 22875 | F18: 23695 | G18: 23695 | H18: 23695 | I18: 23695 | J18: 23695 | K18: 23695 | L18: 23695 | M18: 23695 | N18: 23695 | O18: 23695 | P18: 23695 | Q18: 7656
A19: 6 | B19: Yu Lee Fong | C19: Full-time | D19: =SUM(E19:Q19) -> 273956 | E19: 21385 | F19: 22265 | G19: 22265 | H19: 22265 | I19: 22265 | J19: 22265 | K19: 22265 | L19: 22265 | M19: 22265 | N19: 22265 | O19: 22265 | P19: 22265 | Q19: 7656
A20: 7 | B20: Kong Kar Yee | C20: Full-time | D20: =SUM(E20:Q20) -> 289030.64 | E20: 20388.67 | F20: 16818.67 | G20: 17159.33 | H20: 25477.33 | I20: 25477.33 | J20: 25477.33 | K20: 25477.33 | L20: 25477.33 | M20: 25477.33 | N20: 25477.33 | O20: 25477.33 | P20: 25477.33 | Q20: 5368
A21: 8 | B21: Tsang Tsz Ki | C21: Full-time | D21: =SUM(E21:Q21) -> 99646 | E21: 6350 | F21: 4350 | G21: 6900 | H21: 8950 | I21: 8950 | J21: 8950 | K21: 8950 | L21: 8950 | M21: 8950 | N21: 8950 | O21: 8950 | P21: 8950 | Q21: 1496
A22: 9 | B22: Tsang Lai Yung | C22: Part-time | D22: =SUM(E22:Q22) -> 51856 | E22: 3336 | F22: 3058 | G22: 3336 | H22: 3614 | I22: 3614 | J22: 3614 | K22: 3614 | L22: 3614 | M22: 3614 | N22: 3614 | O22: 3614 | P22: 3614 | Q22: 9600
A23: 10 | B23: Yue Ka Wan Rowenna | C23: Part-time | D23: =SUM(E23:Q23) -> 37262 | E23: 2618 | F23: 3146 | G23: 792 | H23: 3322 | I23: 3322 | J23: 3322 | K23: 3322 | L23: 3322 | M23: 3322 | N23: 3322 | O23: 3322 | P23: 3322 | Q23: 808
D25: =SUM(D15:D24) -> 1823810.6 | E25: =SUM(E15:E24) -> 139167.67 | F25: =SUM(F15:F24) -> 137307.67 | G25: =SUM(G15:G24) -> 138122.33 | H25: =SUM(H15:H24) -> 151298.33 | I25: =SUM(I15:I24) -> 151298.33 | J25: =SUM(J15:J24) -> 151298.33 | K25: =SUM(K15:K24) -> 151298.33 | ... Q25: =SUM(Q15:Q24) -> 47528
D26: ^, per TB | E26: ^ | F26: ^ | G26: ^ | H26: ^ | I26: ^ | J26: ^ | K26: ^ | L26: ^ | M26: ^ | N26: ^ | O26: ^ | P26: ^ | Q26: ^
A29: MPF (Employee portion)
A30: No. | B30: Staff Name | C30: Remarks | D30: Total | E30: 45017 | F30: 45047 | G30: 45078 | H30: 45108 | I30: 45139 | J30: 45170 | K30: 45200 | L30: 45231 | M30: 45261 | N30: 45292 | O30: 45323 | P30: 45352 | Q30: Bonus
A31: =IF(A10>0,A10," ") -> 1 | B31: =IF(B10>0,B10," ") -> Wan Kar Hing | C31: =IF(C10>0,C10," ") -> Director | D31: =SUM(E31:Q31) -> 18000 | E31: =IF(10:10*0.05>1500,1500,10:10*0.05) -> 1500 | F31: =IF(10:10*0.05>1500,1500,10:10*0.05) -> 1500 | G31: =IF(10:10*0.05>1500,1500,10:10*0.05) -> 1500 | H31: =IF(10:10*0.05>1500,1500,10:10*0.05) -> 1500 | I31: =IF(10:10*0.05>1500,1500,10:10*0.05) -> 1500 | J31: =IF(10:10*0.05>1500,1500,10:10*0.05) -> 1500 | K31: =IF(10:10*0.05>1500,1500,10:10*0.05) -> 1500 | L31: =IF(10:10*0.05>1500,1500,10:10*0.05) -> 1500 | ... Q31: =IF(10:10*0.05>1500,1500,10:10*0.05) -> 0
D33: =SUM(D31:D32) -> 18000 | E33: =SUM(E31:E32) -> 1500 | F33: =SUM(F31:F32) -> 1500 | G33: =SUM(G31:G32) -> 1500 | H33: =SUM(H31:H32) -> 1500 | I33: =SUM(I31:I32) -> 1500 | J33: =SUM(J31:J32) -> 1500 | K33: =SUM(K31:K32) -> 1500 | ... Q33: =SUM(Q31:Q32) -> 0
D34: ^, per TB | E34: ^ | F34: ^ | G34: ^ | H34: ^ | I34: ^ | J34: ^ | K34: ^ | L34: ^ | M34: ^ | N34: ^ | O34: ^ | P34: ^ | Q34: ^
A36: =IF(A15>0,A15," ") -> 2 | B36: =IF(B15>0,B15," ") -> Chiu Yin Ning | C36: =IF(C15>0,C15," ") -> Full-time | D36: =SUM(E36:Q36) -> 11474.4 | E36: =IF(15:15*0.05>1500,1500,15:15*0.05) -> 935 | F36: =IF(15:15*0.05>1500,1500,15:15*0.05) -> 935 | G36: =IF(15:15*0.05>1500,1500,15:15*0.05) -> 935 | H36: =IF(15:15*0.05>1500,1500,15:15*0.05) -> 935 | I36: =IF(15:15*0.05>1500,1500,15:15*0.05) -> 935 | J36: =IF(15:15*0.05>1500,1500,15:15*0.05) -> 935 | K36: =IF(15:15*0.05>1500,1500,15:15*0.05) -> 935 | L36: =IF(15:15*0.05>1500,1500,15:15*0.05) -> 935 | ... Q36: =IF(15:15*0.05>1500,1500,15:15*0.05) -> 254.4
A37: =IF(A16>0,A16," ") -> 3 | B37: =IF(B16>0,B16," ") -> Cheung Ka Yee | C37: =IF(C16>0,C16," ") -> Full-time | D37: =SUM(E37:Q37) -> 12228.4 | E37: =IF(16:16*0.05>1500,1500,16:16*0.05) -> 960 | F37: =IF(16:16*0.05>1500,1500,16:16*0.05) -> 1004 | G37: =IF(16:16*0.05>1500,1500,16:16*0.05) -> 1004 | H37: =IF(16:16*0.05>1500,1500,16:16*0.05) -> 1004 | I37: =IF(16:16*0.05>1500,1500,16:16*0.05) -> 1004 | J37: =IF(16:16*0.05>1500,1500,16:16*0.05) -> 1004 | K37: =IF(16:16*0.05>1500,1500,16:16*0.05) -> 1004 | L37: =IF(16:16*0.05>1500,1500,16:16*0.05) -> 1004 | ... Q37: =IF(16:16*0.05>1500,1500,16:16*0.05) -> 224.4
A38: =IF(A17>0,A17," ") -> 4 | B38: =IF(B17>0,B17," ") -> Chiu Ting Chi | C38: =IF(C17>0,C17," ") -> Full-time | D38: =SUM(E38:Q38) -> 15341.4 | E38: =IF(17:17*0.05>1500,1500,17:17*0.05) -> 1215.75 | F38: =IF(17:17*0.05>1500,1500,17:17*0.05) -> 1259.75 | G38: =IF(17:17*0.05>1500,1500,17:17*0.05) -> 1259.75 | H38: =IF(17:17*0.05>1500,1500,17:17*0.05) -> 1259.75 | I38: =IF(17:17*0.05>1500,1500,17:17*0.05) -> 1259.75 | J38: =IF(17:17*0.05>1500,1500,17:17*0.05) -> 1259.75 | K38: =IF(17:17*0.05>1500,1500,17:17*0.05) -> 1259.75 | L38: =IF(17:17*0.05>1500,1500,17:17*0.05) -> 1259.75 | ... Q38: =IF(17:17*0.05>1500,1500,17:17*0.05) -> 268.4
A39: =IF(A18>0,A18," ") -> 5 | B39: =IF(B18>0,B18," ") -> Leung Chung Yi | C39: =IF(C18>0,C18," ") -> Full-time | D39: =SUM(E39:Q39) -> 14558.8 | E39: =IF(18:18*0.05>1500,1500,18:18*0.05) -> 1143.75 | F39: =IF(18:18*0.05>1500,1500,18:18*0.05) -> 1184.75 | G39: =IF(18:18*0.05>1500,1500,18:18*0.05) -> 1184.75 | H39: =IF(18:18*0.05>1500,1500,18:18*0.05) -> 1184.75 | I39: =IF(18:18*0.05>1500,1500,18:18*0.05) -> 1184.75 | J39: =IF(18:18*0.05>1500,1500,18:18*0.05) -> 1184.75 | K39: =IF(18:18*0.05>1500,1500,18:18*0.05) -> 1184.75 | L39: =IF(18:18*0.05>1500,1500,18:18*0.05) -> 1184.75 | ... Q39: =IF(18:18*0.05>1500,1500,18:18*0.05) -> 382.8
A40: =IF(A19>0,A19," ") -> 6 | B40: =IF(B19>0,B19," ") -> Yu Lee Fong | C40: =IF(C19>0,C19," ") -> Full-time | D40: =SUM(E40:Q40) -> 13697.8 | E40: =IF(19:19*0.05>1500,1500,19:19*0.05) -> 1069.25 | F40: =IF(19:19*0.05>1500,1500,19:19*0.05) -> 1113.25 | G40: =IF(19:19*0.05>1500,1500,19:19*0.05) -> 1113.25 | H40: =IF(19:19*0.05>1500,1500,19:19*0.05) -> 1113.25 | I40: =IF(19:19*0.05>1500,1500,19:19*0.05) -> 1113.25 | J40: =IF(19:19*0.05>1500,1500,19:19*0.05) -> 1113.25 | K40: =IF(19:19*0.05>1500,1500,19:19*0.05) -> 1113.25 | L40: =IF(19:19*0.05>1500,1500,19:19*0.05) -> 1113.25 | ... Q40: =IF(19:19*0.05>1500,1500,19:19*0.05) -> 382.8
A41: =IF(A20>0,A20," ") -> 7 | B41: =IF(B20>0,B20," ") -> Kong Kar Yee | C41: =IF(C20>0,C20," ") -> Full-time | D41: =SUM(E41:Q41) -> 14451.532 | E41: =IF(20:20*0.05>1500,1500,20:20*0.05) -> 1019.4335 | F41: =IF(20:20*0.05>1500,1500,20:20*0.05) -> 840.9335 | G41: =IF(20:20*0.05>1500,1500,20:20*0.05) -> 857.9665 | H41: =IF(20:20*0.05>1500,1500,20:20*0.05) -> 1273.8665 | I41: =IF(20:20*0.05>1500,1500,20:20*0.05) -> 1273.8665 | J41: =IF(20:20*0.05>1500,1500,20:20*0.05) -> 1273.8665 | K41: =IF(20:20*0.05>1500,1500,20:20*0.05) -> 1273.8665 | L41: =IF(20:20*0.05>1500,1500,20:20*0.05) -> 1273.8665 | ... Q41: =IF(20:20*0.05>1500,1500,20:20*0.05) -> 268.4
A42: =IF(A21>0,A21," ") -> 8 | B42: =IF(B21>0,B21," ") -> Tsang Tsz Ki | C42: =IF(C21>0,C21," ") -> Full-time | D42: =SUM(E42:Q42) -> 4982.3 | E42: =IF(21:21*0.05>1500,1500,21:21*0.05) -> 317.5 | F42: =IF(21:21*0.05>1500,1500,21:21*0.05) -> 217.5 | G42: =IF(21:21*0.05>1500,1500,21:21*0.05) -> 345 | H42: =IF(21:21*0.05>1500,1500,21:21*0.05) -> 447.5 | I42: =IF(21:21*0.05>1500,1500,21:21*0.05) -> 447.5 | J42: =IF(21:21*0.05>1500,1500,21:21*0.05) -> 447.5 | K42: =IF(21:21*0.05>1500,1500,21:21*0.05) -> 447.5 | L42: =IF(21:21*0.05>1500,1500,21:21*0.05) -> 447.5 | ... Q42: =IF(21:21*0.05>1500,1500,21:21*0.05) -> 74.8
A43: =IF(A22>0,A22," ") -> 9 | B43: =IF(B22>0,B22," ") -> Tsang Lai Yung | C43: =IF(C22>0,C22," ") -> Part-time | D43: =SUM(E43:Q43) -> 2592.8 | E43: =IF(22:22*0.05>1500,1500,22:22*0.05) -> 166.8 | F43: =IF(22:22*0.05>1500,1500,22:22*0.05) -> 152.9 | G43: =IF(22:22*0.05>1500,1500,22:22*0.05) -> 166.8 | H43: =IF(22:22*0.05>1500,1500,22:22*0.05) -> 180.7 | I43: =IF(22:22*0.05>1500,1500,22:22*0.05) -> 180.7 | J43: =IF(22:22*0.05>1500,1500,22:22*0.05) -> 180.7 | K43: =IF(22:22*0.05>1500,1500,22:22*0.05) -> 180.7 | L43: =IF(22:22*0.05>1500,1500,22:22*0.05) -> 180.7 | ... Q43: =IF(22:22*0.05>1500,1500,22:22*0.05) -> 480
A44: =IF(A23>0,A23," ") -> 10 | B44: =IF(B23>0,B23," ") -> Yue Ka Wan Rowenna | C44: =IF(C23>0,C23," ") -> Part-time | D44: =SUM(E44:Q44) -> 1863.1 | E44: =IF(23:23*0.05>1500,1500,23:23*0.05) -> 130.9 | F44: =IF(23:23*0.05>1500,1500,23:23*0.05) -> 157.3 | G44: =IF(23:23*0.05>1500,1500,23:23*0.05) -> 39.6 | H44: =IF(23:23*0.05>1500,1500,23:23*0.05) -> 166.1 | I44: =IF(23:23*0.05>1500,1500,23:23*0.05) -> 166.1 | J44: =IF(23:23*0.05>1500,1500,23:23*0.05) -> 166.1 | K44: =IF(23:23*0.05>1500,1500,23:23*0.05) -> 166.1 | L44: =IF(23:23*0.05>1500,1500,23:23*0.05) -> 166.1 | ... Q44: =IF(23:23*0.05>1500,1500,23:23*0.05) -> 40.4
D46: =SUM(D36:D45) -> 91190.532 | E46: =SUM(E36:E45) -> 6958.3835 | F46: =SUM(F36:F45) -> 6865.3835 | G46: =SUM(G36:G45) -> 6906.1165 | H46: =SUM(H36:H45) -> 7564.9165 | I46: =SUM(I36:I45) -> 7564.9165 | J46: =SUM(J36:J45) -> 7564.9165 | K46: =SUM(K36:K45) -> 7564.9165 | ... Q46: =SUM(Q36:Q45) -> 2376.4
D47: ^ | E47: ^ | F47: ^ | G47: ^ | H47: ^ | I47: ^ | J47: ^ | K47: ^ | L47: ^ | M47: ^ | N47: ^ | O47: ^ | P47: ^ | Q47: ^
A50: MPF (Employer portion)
A51: No. | B51: Staff Name | C51: Remarks | D51: Total | E51: 45017 | F51: 45047 | G51: 45078 | H51: 45108 | I51: 45139 | J51: 45170 | K51: 45200 | L51: 45231 | M51: 45261 | N51: 45292 | O51: 45323 | P51: 45352 | Q51: Bonus
A52: =IF(A10>0,A10," ") -> 1 | B52: =IF(B10>0,B10," ") -> Wan Kar Hing | C52: =IF(C10>0,C10," ") -> Director | D52: =SUM(E52:Q52) -> 18000 | E52: =IF(10:10*0.05>1500,1500,10:10*0.05) -> 1500 | F52: =IF(10:10*0.05>1500,1500,10:10*0.05) -> 1500 | G52: =IF(10:10*0.05>1500,1500,10:10*0.05) -> 1500 | H52: =IF(10:10*0.05>1500,1500,10:10*0.05) -> 1500 | I52: =IF(10:10*0.05>1500,1500,10:10*0.05) -> 1500 | J52: =IF(10:10*0.05>1500,1500,10:10*0.05) -> 1500 | K52: =IF(10:10*0.05>1500,1500,10:10*0.05) -> 1500 | L52: =IF(10:10*0.05>1500,1500,10:10*0.05) -> 1500 | ... Q52: =IF(10:10*0.05>1500,1500,10:10*0.05) -> 0
D54: =SUM(D52:D53) -> 18000 | E54: =SUM(E52:E53) -> 1500 | F54: =SUM(F52:F53) -> 1500 | G54: =SUM(G52:G53) -> 1500 | H54: =SUM(H52:H53) -> 1500 | I54: =SUM(I52:I53) -> 1500 | J54: =SUM(J52:J53) -> 1500 | K54: =SUM(K52:K53) -> 1500 | ... Q54: =SUM(Q52:Q53) -> 0
D55: ^, per TB | E55: ^ | F55: ^ | G55: ^ | H55: ^ | I55: ^ | J55: ^ | K55: ^ | L55: ^ | M55: ^ | N55: ^ | O55: ^ | P55: ^ | Q55: ^
A57: =IF(A15>0,A15," ") -> 2 | B57: =IF(B15>0,B15," ") -> Chiu Yin Ning | C57: =IF(C15>0,C15," ") -> Full-time | D57: =SUM(E57:Q57) -> 11474.4 | E57: =IF(15:15*0.05>1500,1500,15:15*0.05) -> 935 | F57: =IF(15:15*0.05>1500,1500,15:15*0.05) -> 935 | G57: =IF(15:15*0.05>1500,1500,15:15*0.05) -> 935 | H57: =IF(15:15*0.05>1500,1500,15:15*0.05) -> 935 | I57: =IF(15:15*0.05>1500,1500,15:15*0.05) -> 935 | J57: =IF(15:15*0.05>1500,1500,15:15*0.05) -> 935 | K57: =IF(15:15*0.05>1500,1500,15:15*0.05) -> 935 | L57: =IF(15:15*0.05>1500,1500,15:15*0.05) -> 935 | ... Q57: =IF(15:15*0.05>1500,1500,15:15*0.05) -> 254.4
A58: =IF(A16>0,A16," ") -> 3 | B58: =IF(B16>0,B16," ") -> Cheung Ka Yee | C58: =IF(C16>0,C16," ") -> Full-time | D58: =SUM(E58:Q58) -> 12228.4 | E58: =IF(16:16*0.05>1500,1500,16:16*0.05) -> 960 | F58: =IF(16:16*0.05>1500,1500,16:16*0.05) -> 1004 | G58: =IF(16:16*0.05>1500,1500,16:16*0.05) -> 1004 | H58: =IF(16:16*0.05>1500,1500,16:16*0.05) -> 1004 | I58: =IF(16:16*0.05>1500,1500,16:16*0.05) -> 1004 | J58: =IF(16:16*0.05>1500,1500,16:16*0.05) -> 1004 | K58: =IF(16:16*0.05>1500,1500,16:16*0.05) -> 1004 | L58: =IF(16:16*0.05>1500,1500,16:16*0.05) -> 1004 | ... Q58: =IF(16:16*0.05>1500,1500,16:16*0.05) -> 224.4
A59: =IF(A17>0,A17," ") -> 4 | B59: =IF(B17>0,B17," ") -> Chiu Ting Chi | C59: =IF(C17>0,C17," ") -> Full-time | D59: =SUM(E59:Q59) -> 15341.4 | E59: =IF(17:17*0.05>1500,1500,17:17*0.05) -> 1215.75 | F59: =IF(17:17*0.05>1500,1500,17:17*0.05) -> 1259.75 | G59: =IF(17:17*0.05>1500,1500,17:17*0.05) -> 1259.75 | H59: =IF(17:17*0.05>1500,1500,17:17*0.05) -> 1259.75 | I59: =IF(17:17*0.05>1500,1500,17:17*0.05) -> 1259.75 | J59: =IF(17:17*0.05>1500,1500,17:17*0.05) -> 1259.75 | K59: =IF(17:17*0.05>1500,1500,17:17*0.05) -> 1259.75 | L59: =IF(17:17*0.05>1500,1500,17:17*0.05) -> 1259.75 | ... Q59: =IF(17:17*0.05>1500,1500,17:17*0.05) -> 268.4
A60: =IF(A18>0,A18," ") -> 5 | B60: =IF(B18>0,B18," ") -> Leung Chung Yi | C60: =IF(C18>0,C18," ") -> Full-time | D60: =SUM(E60:Q60) -> 14558.8 | E60: =IF(18:18*0.05>1500,1500,18:18*0.05) -> 1143.75 | F60: =IF(18:18*0.05>1500,1500,18:18*0.05) -> 1184.75 | G60: =IF(18:18*0.05>1500,1500,18:18*0.05) -> 1184.75 | H60: =IF(18:18*0.05>1500,1500,18:18*0.05) -> 1184.75 | I60: =IF(18:18*0.05>1500,1500,18:18*0.05) -> 1184.75 | J60: =IF(18:18*0.05>1500,1500,18:18*0.05) -> 1184.75 | K60: =IF(18:18*0.05>1500,1500,18:18*0.05) -> 1184.75 | L60: =IF(18:18*0.05>1500,1500,18:18*0.05) -> 1184.75 | ... Q60: =IF(18:18*0.05>1500,1500,18:18*0.05) -> 382.8
A61: =IF(A19>0,A19," ") -> 6 | B61: =IF(B19>0,B19," ") -> Yu Lee Fong | C61: =IF(C19>0,C19," ") -> Full-time | D61: =SUM(E61:Q61) -> 13697.8 | E61: =IF(19:19*0.05>1500,1500,19:19*0.05) -> 1069.25 | F61: =IF(19:19*0.05>1500,1500,19:19*0.05) -> 1113.25 | G61: =IF(19:19*0.05>1500,1500,19:19*0.05) -> 1113.25 | H61: =IF(19:19*0.05>1500,1500,19:19*0.05) -> 1113.25 | I61: =IF(19:19*0.05>1500,1500,19:19*0.05) -> 1113.25 | J61: =IF(19:19*0.05>1500,1500,19:19*0.05) -> 1113.25 | K61: =IF(19:19*0.05>1500,1500,19:19*0.05) -> 1113.25 | L61: =IF(19:19*0.05>1500,1500,19:19*0.05) -> 1113.25 | ... Q61: =IF(19:19*0.05>1500,1500,19:19*0.05) -> 382.8
A62: =IF(A20>0,A20," ") -> 7 | B62: =IF(B20>0,B20," ") -> Kong Kar Yee | C62: =IF(C20>0,C20," ") -> Full-time | D62: =SUM(E62:Q62) -> 14451.532 | E62: =IF(20:20*0.05>1500,1500,20:20*0.05) -> 1019.4335 | F62: =IF(20:20*0.05>1500,1500,20:20*0.05) -> 840.9335 | G62: =IF(20:20*0.05>1500,1500,20:20*0.05) -> 857.9665 | H62: =IF(20:20*0.05>1500,1500,20:20*0.05) -> 1273.8665 | I62: =IF(20:20*0.05>1500,1500,20:20*0.05) -> 1273.8665 | J62: =IF(20:20*0.05>1500,1500,20:20*0.05) -> 1273.8665 | K62: =IF(20:20*0.05>1500,1500,20:20*0.05) -> 1273.8665 | L62: =IF(20:20*0.05>1500,1500,20:20*0.05) -> 1273.8665 | ... Q62: =IF(20:20*0.05>1500,1500,20:20*0.05) -> 268.4
A63: =IF(A21>0,A21," ") -> 8 | B63: =IF(B21>0,B21," ") -> Tsang Tsz Ki | C63: =IF(C21>0,C21," ") -> Full-time | D63: =SUM(E63:Q63) -> 4982.3 | E63: =IF(21:21*0.05>1500,1500,21:21*0.05) -> 317.5 | F63: =IF(21:21*0.05>1500,1500,21:21*0.05) -> 217.5 | G63: =IF(21:21*0.05>1500,1500,21:21*0.05) -> 345 | H63: =IF(21:21*0.05>1500,1500,21:21*0.05) -> 447.5 | I63: =IF(21:21*0.05>1500,1500,21:21*0.05) -> 447.5 | J63: =IF(21:21*0.05>1500,1500,21:21*0.05) -> 447.5 | K63: =IF(21:21*0.05>1500,1500,21:21*0.05) -> 447.5 | L63: =IF(21:21*0.05>1500,1500,21:21*0.05) -> 447.5 | ... Q63: =IF(21:21*0.05>1500,1500,21:21*0.05) -> 74.8
A64: =IF(A22>0,A22," ") -> 9 | B64: =IF(B22>0,B22," ") -> Tsang Lai Yung | C64: =IF(C22>0,C22," ") -> Part-time | D64: =SUM(E64:Q64) -> 2592.8 | E64: =IF(22:22*0.05>1500,1500,22:22*0.05) -> 166.8 | F64: =IF(22:22*0.05>1500,1500,22:22*0.05) -> 152.9 | G64: =IF(22:22*0.05>1500,1500,22:22*0.05) -> 166.8 | H64: =IF(22:22*0.05>1500,1500,22:22*0.05) -> 180.7 | I64: =IF(22:22*0.05>1500,1500,22:22*0.05) -> 180.7 | J64: =IF(22:22*0.05>1500,1500,22:22*0.05) -> 180.7 | K64: =IF(22:22*0.05>1500,1500,22:22*0.05) -> 180.7 | L64: =IF(22:22*0.05>1500,1500,22:22*0.05) -> 180.7 | ... Q64: =IF(22:22*0.05>1500,1500,22:22*0.05) -> 480
A65: =IF(A23>0,A23," ") -> 10 | B65: =IF(B23>0,B23," ") -> Yue Ka Wan Rowenna | C65: =IF(C23>0,C23," ") -> Part-time | D65: =SUM(E65:Q65) -> 1863.1 | E65: =IF(23:23*0.05>1500,1500,23:23*0.05) -> 130.9 | F65: =IF(23:23*0.05>1500,1500,23:23*0.05) -> 157.3 | G65: =IF(23:23*0.05>1500,1500,23:23*0.05) -> 39.6 | H65: =IF(23:23*0.05>1500,1500,23:23*0.05) -> 166.1 | I65: =IF(23:23*0.05>1500,1500,23:23*0.05) -> 166.1 | J65: =IF(23:23*0.05>1500,1500,23:23*0.05) -> 166.1 | K65: =IF(23:23*0.05>1500,1500,23:23*0.05) -> 166.1 | L65: =IF(23:23*0.05>1500,1500,23:23*0.05) -> 166.1 | ... Q65: =IF(23:23*0.05>1500,1500,23:23*0.05) -> 40.4
D67: =SUM(D57:D66) -> 91190.532 | E67: =SUM(E57:E66) -> 6958.3835 | F67: =SUM(F57:F66) -> 6865.3835 | G67: =SUM(G57:G66) -> 6906.1165 | H67: =SUM(H57:H66) -> 7564.9165 | I67: =SUM(I57:I66) -> 7564.9165 | J67: =SUM(J57:J66) -> 7564.9165 | K67: =SUM(K57:K66) -> 7564.9165 | ... Q67: =SUM(Q57:Q66) -> 2376.4
D68: ^, per TB | E68: ^ | F68: ^ | G68: ^ | H68: ^ | I68: ^ | J68: ^ | K68: ^ | L68: ^ | M68: ^ | N68: ^ | O68: ^ | P68: ^ | Q68: ^
A70: Total MPF | C70: per bank | D70: =33:33+46:46+54:54+67:67 -> 218381.06 | E70: =33:33+46:46+54:54+67:67 -> 16916.767 | F70: =33:33+46:46+54:54+67:67 -> 16730.767 | G70: =33:33+46:46+54:54+67:67 -> 16812.233 | H70: =33:33+46:46+54:54+67:67 -> 18129.833 | I70: =33:33+46:46+54:54+67:67 -> 18129.833 | J70: =33:33+46:46+54:54+67:67 -> 18129.833 | K70: =33:33+46:46+54:54+67:67 -> 18129.833 | ... Q70: =33:33+46:46+54:54+67:67 -> 4752.8
D71: ^ | E71: ^ | F71: ^ | G71: ^ | H71: ^ | I71: ^ | J71: ^ | K71: ^ | L71: ^ | M71: ^ | N71: ^ | O71: ^ | P71: ^ | Q71: ^
A74: Net salaries (per bank)
A75: No. | B75: Staff Name | C75: Remarks | D75: Total | E75: 45017 | F75: 45047 | G75: 45078 | H75: 45108 | I75: 45139 | J75: 45170 | K75: 45200 | L75: 45231 | M75: 45261 | N75: 45292 | O75: 45323 | P75: 45352 | Q75: Bonus
A76: =IF(A10>0,A10," ") -> 1 | B76: =IF(B10>0,B10," ") -> Wan Kar Hing | C76: =IF(C10>0,C10," ") -> Director | D76: =SUM(E76:Q76) -> 582000 | E76: =10:10-31:31 -> 48500 | F76: =10:10-31:31 -> 48500 | G76: =10:10-31:31 -> 48500 | H76: =10:10-31:31 -> 48500 | I76: =10:10-31:31 -> 48500 | J76: =10:10-31:31 -> 48500 | K76: =10:10-31:31 -> 48500 | L76: =10:10-31:31 -> 48500 | ... Q76: =10:10-31:31 -> 0
D78: =SUM(D76:D77) -> 582000 | E78: =SUM(E76:E77) -> 48500 | F78: =SUM(F76:F77) -> 48500 | G78: =SUM(G76:G77) -> 48500 | H78: =SUM(H76:H77) -> 48500 | I78: =SUM(I76:I77) -> 48500 | J78: =SUM(J76:J77) -> 48500 | K78: =SUM(K76:K77) -> 48500 | ... Q78: =SUM(Q76:Q77) -> 0
D79: ^ | E79: ^ | F79: ^ | G79: ^ | H79: ^ | I79: ^ | J79: ^ | K79: ^ | L79: ^ | M79: ^ | N79: ^ | O79: ^ | P79: ^ | Q79: ^
A81: =IF(A15>0,A15," ") -> 2 | B81: =IF(B15>0,B15," ") -> Chiu Yin Ning | C81: =IF(C15>0,C15," ") -> Full-time | D81: =SUM(E81:Q81) -> 218013.6 | E81: =15:15-36:36 -> 17765 | F81: =15:15-36:36 -> 17765 | G81: =15:15-36:36 -> 17765 | H81: =15:15-36:36 -> 17765 | I81: =15:15-36:36 -> 17765 | J81: =15:15-36:36 -> 17765 | K81: =15:15-36:36 -> 17765 | L81: =15:15-36:36 -> 17765 | ... Q81: =15:15-36:36 -> 4833.6
A82: =IF(A16>0,A16," ") -> 3 | B82: =IF(B16>0,B16," ") -> Cheung Ka Yee | C82: =IF(C16>0,C16," ") -> Full-time | D82: =SUM(E82:Q82) -> 232339.6 | E82: =16:16-37:37 -> 18240 | F82: =16:16-37:37 -> 19076 | G82: =16:16-37:37 -> 19076 | H82: =16:16-37:37 -> 19076 | I82: =16:16-37:37 -> 19076 | J82: =16:16-37:37 -> 19076 | K82: =16:16-37:37 -> 19076 | L82: =16:16-37:37 -> 19076 | ... Q82: =16:16-37:37 -> 4263.6
A83: =IF(A17>0,A17," ") -> 4 | B83: =IF(B17>0,B17," ") -> Chiu Ting Chi | C83: =IF(C17>0,C17," ") -> Full-time | D83: =SUM(E83:Q83) -> 291486.6 | E83: =17:17-38:38 -> 23099.25 | F83: =17:17-38:38 -> 23935.25 | G83: =17:17-38:38 -> 23935.25 | H83: =17:17-38:38 -> 23935.25 | I83: =17:17-38:38 -> 23935.25 | J83: =17:17-38:38 -> 23935.25 | K83: =17:17-38:38 -> 23935.25 | L83: =17:17-38:38 -> 23935.25 | ... Q83: =17:17-38:38 -> 5099.6
A84: =IF(A18>0,A18," ") -> 5 | B84: =IF(B18>0,B18," ") -> Leung Chung Yi | C84: =IF(C18>0,C18," ") -> Full-time | D84: =SUM(E84:Q84) -> 276617.2 | E84: =18:18-39:39 -> 21731.25 | F84: =18:18-39:39 -> 22510.25 | G84: =18:18-39:39 -> 22510.25 | H84: =18:18-39:39 -> 22510.25 | I84: =18:18-39:39 -> 22510.25 | J84: =18:18-39:39 -> 22510.25 | K84: =18:18-39:39 -> 22510.25 | L84: =18:18-39:39 -> 22510.25 | ... Q84: =18:18-39:39 -> 7273.2
A85: =IF(A19>0,A19," ") -> 6 | B85: =IF(B19>0,B19," ") -> Yu Lee Fong | C85: =IF(C19>0,C19," ") -> Full-time | D85: =SUM(E85:Q85) -> 260258.2 | E85: =19:19-40:40 -> 20315.75 | F85: =19:19-40:40 -> 21151.75 | G85: =19:19-40:40 -> 21151.75 | H85: =19:19-40:40 -> 21151.75 | I85: =19:19-40:40 -> 21151.75 | J85: =19:19-40:40 -> 21151.75 | K85: =19:19-40:40 -> 21151.75 | L85: =19:19-40:40 -> 21151.75 | ... Q85: =19:19-40:40 -> 7273.2
A86: =IF(A20>0,A20," ") -> 7 | B86: =IF(B20>0,B20," ") -> Kong Kar Yee | C86: =IF(C20>0,C20," ") -> Full-time | D86: =SUM(E86:Q86) -> 274579.11 | E86: =20:20-41:41 -> 19369.236 | F86: =20:20-41:41 -> 15977.736 | G86: =20:20-41:41 -> 16301.364 | H86: =20:20-41:41 -> 24203.464 | I86: =20:20-41:41 -> 24203.464 | J86: =20:20-41:41 -> 24203.464 | K86: =20:20-41:41 -> 24203.464 | L86: =20:20-41:41 -> 24203.464 | ... Q86: =20:20-41:41 -> 5099.6
A87: =IF(A21>0,A21," ") -> 8 | B87: =IF(B21>0,B21," ") -> Tsang Tsz Ki | C87: =IF(C21>0,C21," ") -> Full-time | D87: =SUM(E87:Q87) -> 94663.7 | E87: =21:21-42:42 -> 6032.5 | F87: =21:21-42:42 -> 4132.5 | G87: =21:21-42:42 -> 6555 | H87: =21:21-42:42 -> 8502.5 | I87: =21:21-42:42 -> 8502.5 | J87: =21:21-42:42 -> 8502.5 | K87: =21:21-42:42 -> 8502.5 | L87: =21:21-42:42 -> 8502.5 | ... Q87: =21:21-42:42 -> 1421.2
A88: =IF(A22>0,A22," ") -> 9 | B88: =IF(B22>0,B22," ") -> Tsang Lai Yung | C88: =IF(C22>0,C22," ") -> Part-time | D88: =SUM(E88:Q88) -> 49263.2 | E88: =22:22-43:43 -> 3169.2 | F88: =22:22-43:43 -> 2905.1 | G88: =22:22-43:43 -> 3169.2 | H88: =22:22-43:43 -> 3433.3 | I88: =22:22-43:43 -> 3433.3 | J88: =22:22-43:43 -> 3433.3 | K88: =22:22-43:43 -> 3433.3 | L88: =22:22-43:43 -> 3433.3 | ... Q88: =22:22-43:43 -> 9120
A89: =IF(A23>0,A23," ") -> 10 | B89: =IF(B23>0,B23," ") -> Yue Ka Wan Rowenna | C89: =IF(C23>0,C23," ") -> Part-time | D89: =SUM(E89:Q89) -> 35398.9 | E89: =23:23-44:44 -> 2487.1 | F89: =23:23-44:44 -> 2988.7 | G89: =23:23-44:44 -> 752.4 | H89: =23:23-44:44 -> 3155.9 | I89: =23:23-44:44 -> 3155.9 | J89: =23:23-44:44 -> 3155.9 | K89: =23:23-44:44 -> 3155.9 | L89: =23:23-44:44 -> 3155.9 | ... Q89: =23:23-44:44 -> 767.6
D91: =SUM(D81:D90) -> 1732620.1 | E91: =SUM(E81:E90) -> 132209.29 | F91: =SUM(F81:F90) -> 130442.29 | G91: =SUM(G81:G90) -> 131216.21 | H91: =SUM(H81:H90) -> 143733.41 | I91: =SUM(I81:I90) -> 143733.41 | J91: =SUM(J81:J90) -> 143733.41 | K91: =SUM(K81:K90) -> 143733.41 | ... Q91: =SUM(Q81:Q90) -> 45151.6
D92: ^ | E92: ^ | F92: ^ | G92: ^ | H92: ^ | I92: ^ | J92: ^ | K92: ^ | L92: ^ | M92: ^ | N92: ^ | O92: ^ | P92: ^ | Q92: ^
O94: Accruals
O95: Salaries - MPF (EE) | P95: =SUM(P36:P44) -> 7564.9165
O96: MPF (ER) | P96: =SUM(P57:P65) -> 7564.9165
O97: Director's remuneration | P97: =P31+P52+P76 -> 51500
O98: Salaries | P98: =SUM(P81:P89) -> 143733.41
P100: =SUM(P95:P98) -> 210363.25
P101: ^

Sheet Chart of Accounts
A1: Account Description | B1: Account ID
A2: HSB HKD CA | B2: 1000
A3: HSB HKD SA | B3: 1010
A4: HSBC CR. CARD | B4: 1020
A5: BOC HKD SA | B5: 1030
A6: Interbank | B6: 1080
A7: Cash | B7: 1090
A8: Trade receivable | B8: 1100
A9: Other receivables | B9: 1120
A10: Amt due fr related co | B10: 1130
A11: Trade deposit paid | B11: 1150
A12: Rental & utilities deposit | B12: 1200
A13: Prepayment | B13: 1300
... A93: Income tax expenses | B93: 9000
